Workbook

Sheet Financial Statements
B4: 42005 | C4: 42370 | D4: 42736 | E4: 43101 | F4: 43466 | G4: 43831 | H4: 44197 | I4: 44562 | J4: 44927 | K4: 45292 | L4: 45658 | M4: 46023 | N4: 46388 | O4: 46753 | P4: 47119
A5: Revenues
A6: Total Revenues | B6: 4682 | C6: 5010 | D6: 6910 | E6: 9714 | F6: 11716 | G6: 10918 | H6: 16675 | I6: 26914 | J6: 26974 | K6: 60922 | L6: =K6*(1+'Forecast Assumptions'!L3) -> 67014.2 | M6: =L6*(1+'Forecast Assumptions'!M3) -> 77066.33 | N6: =M6*(1+'Forecast Assumptions'!N3) -> 92479.596 | O6: =N6*(1+'Forecast Assumptions'!O3) -> 115599.5 | P6: =O6*(1+'Forecast Assumptions'!P3) -> 150279.34
A7: Cost Of Revenues | B7: 2083 | C7: 2199 | D7: 2847 | E7: 3892 | F7: 4545 | G7: 4150 | H7: 6118 | I7: 9439 | J7: 11618 | K7: 16621 | L7: =L6*'Forecast Assumptions'!L4 -> 23454.97 | M7: =M6*'Forecast Assumptions'!M4 -> 26973.215 | N7: =N6*'Forecast Assumptions'!N4 -> 32367.859 | O7: =O6*'Forecast Assumptions'!O4 -> 40459.823 | P7: =P6*'Forecast Assumptions'!P4 -> 52597.77
A8: Gross Profit | B8: =B6-B7 -> 2599 | C8: =C6-C7 -> 2811 | D8: =D6-D7 -> 4063 | E8: =E6-E7 -> 5822 | F8: =F6-F7 -> 7171 | G8: =G6-G7 -> 6768 | H8: =H6-H7 -> 10557 | I8: =I6-I7 -> 17475 | ... P8: =P6-P7 -> 97681.573 | S8: 2025 | T8: 2026 | U8: 2027 | V8: 2028 | W8: 2029
A9: Operating Expenses & Income | R9: Change in NCCA | S9: =(L30+L31+L32+L33)-(K30+K31+K32+K33) -> 1743.26 | T9: =(M30+M31+M32+M33)-(L30+L31+L32+L33) -> 3015.639 | U9: =(N30+N31+N32+N33)-(M30+M31+M32+M33) -> 4623.9798 | V9: =(O30+O31+O32+O33)-(N30+N31+N32+N33) -> 6935.9697 | W9: =(P30+P31+P32+P33)-(O30+O31+O32+O33) -> 10403.955
A10: Selling General & Admin Expenses | B10: 480 | C10: 602 | D10: 663 | E10: 815 | F10: 991 | G10: 1093 | H10: 1912 | I10: 2166 | J10: 2440 | K10: 2654 | L10: =L6*'Forecast Assumptions'!L5 -> 6701.42 | M10: =M6*'Forecast Assumptions'!M5 -> 7706.633 | N10: =N6*'Forecast Assumptions'!N5 -> 9247.9596 | O10: =O6*'Forecast Assumptions'!O5 -> 11559.95 | P10: =P6*'Forecast Assumptions'!P5 -> 15027.934 | R10: Change in CL | S10: =L56-K56 -> 7195169.5 | T10: =M56-L56 -> 7567020.1 | U10: =N56-M56 -> 3724872.6 | V10: =O56-N56 -> 8477296.3 | W10: =P56-O56 -> 577997.48
A11: R&D Expenses | B11: 1360 | C11: 1331 | D11: 1463 | E11: 1797 | F11: 2376 | G11: 2829 | H11: 3924 | I11: 5268 | J11: 7339 | K11: 8675 | L11: =L6*'Forecast Assumptions'!L6 -> 13402.84 | M11: =M6*'Forecast Assumptions'!M6 -> 15413.266 | N11: =N6*'Forecast Assumptions'!N6 -> 18495.919 | O11: =O6*'Forecast Assumptions'!O6 -> 23119.899 | P11: =P6*'Forecast Assumptions'!P6 -> 30055.869 | R11: Change in NCWC | S11: =S9-S10 -> -7193426.2 | T11: =T9-T10 -> -7564004.4 | U11: =U9-U10 -> -3720248.6 | V11: =V9-V10 -> -8470360.3 | W11: =W9-W10 -> -567593.52
A12: Total Operating Expenses | B12: =B10+B11 -> 1840 | C12: =C10+C11 -> 1933 | D12: =D10+D11 -> 2126 | E12: =E10+E11 -> 2612 | F12: =F10+F11 -> 3367 | G12: =G10+G11 -> 3922 | H12: =H10+H11 -> 5836 | I12: =I10+I11 -> 7434 | ... P12: =P10+P11 -> 45083.803
A13: Operating Income | B13: =B8-B12 -> 759 | C13: =C8-C12 -> 878 | D13: =D8-D12 -> 1937 | E13: =E8-E12 -> 3210 | F13: =F8-F12 -> 3804 | G13: =G8-G12 -> 2846 | H13: =H8-H12 -> 4721 | I13: =I8-I12 -> 10041 | ... P13: =P8-P12 -> 52597.77
A14: Earnings from Continuing Operations
A15: Interest Expense | B15: -46 | C15: -47 | D15: -58 | E15: -61 | F15: -58 | G15: -52 | H15: -184 | I15: -236 | J15: -262 | K15: -257 | L15: =$K$15 -> -257 | M15: =L15 -> -257 | N15: =M15 -> -257 | O15: =N15 -> -257 | P15: =O15 -> -257
A16: Interest And Investment Income | B16: 28 | C16: 39 | D16: 54 | E16: 69 | F16: 136 | G16: 178 | H16: 57 | I16: 29 | J16: 267 | K16: 866 | L16: 866 | M16: =L16 -> 866 | N16: =M16 -> 866 | O16: =N16 -> 866 | P16: =O16 -> 866
A17: Net Interest Expenses | B17: =B15+B16 -> -18 | C17: =C15+C16 -> -8 | D17: =D15+D16 -> -4 | E17: =E15+E16 -> 8 | F17: =F15+F16 -> 78 | G17: =G15+G16 -> 126 | H17: =H15+H16 -> -127 | I17: =I15+I16 -> -207 | ... P17: =P15+P16 -> 609
A18: Other Non Operating Income (Expenses) | B18: 14 | C18: 4 | D18: -4 | E18: -22 | F18: 14 | G18: 0 | H18: 4 | I18: 7 | J18: -3 | K18: -1 | L18: 0 | M18: =L18 -> 0 | N18: =M18 -> 0 | O18: =N18 -> 0 | P18: =O18 -> 0
A19: EBT, Incl. Unusual Items | B19: =B13+B17+B18 -> 755 | C19: =C13+C17+C18 -> 874 | D19: =D13+D17+D18 -> 1929 | E19: =E13+E17+E18 -> 3196 | F19: =F13+F17+F18 -> 3896 | G19: =G13+G17+G18 -> 2972 | H19: =H13+H17+H18 -> 4598 | I19: =I13+I17+I18 -> 9841 | ... K19: =K13+K17+K18 -> 33580 | L19: =L13+L17 -> 24063.97 | M19: =M13+M17 -> 27582.216 | N19: =N13+N17 -> 32976.859 | O19: =O13+O17 -> 41068.823 | P19: =P13+P17 -> 53206.77
A20: Income Tax Expense | B20: 124 | C20: 260 | D20: 263 | E20: 149 | F20: -245 | G20: 176 | H20: 266 | I20: 89 | J20: 1211 | K20: 3820 | L20: ='Financial Statements'!L19*'Forecast Assumptions'!L9 -> 5053.4337 | M20: ='Financial Statements'!M19*'Forecast Assumptions'!M9 -> 6068.0874 | N20: ='Financial Statements'!N19*'Forecast Assumptions'!N9 -> 7584.6775 | O20: ='Financial Statements'!O19*'Forecast Assumptions'!O9 -> 9856.5176 | P20: ='Financial Statements'!P19*'Forecast Assumptions'!P9 -> 13301.693
A21: Net Income | B21: =B19-B20 -> 631 | C21: =C19-C20 -> 614 | D21: =D19-D20 -> 1666 | E21: =E19-E20 -> 3047 | F21: =F19-F20 -> 4141 | G21: =G19-G20 -> 2796 | H21: =H19-H20 -> 4332 | I21: =I19-I20 -> 9752 | ... P21: =P19-P20 -> 39905.078
B27: 42005 | C27: 42370 | D27: 42736 | E27: 43101 | F27: 43466 | G27: 43831 | H27: 44197 | I27: 44562 | J27: 44927 | K27: 45292 | L27: 45658 | M27: 46023 | N27: 46388 | O27: 46753 | P27: 47119
A29: Total Cash & ST Investments | B29: 4623 | C29: 5037 | D29: 6798 | E29: 7108 | F29: 7422 | G29: 10897 | H29: 11561 | I29: 21208 | J29: 13296 | K29: 25984 | L29: =K29 -> 25984 | M29: =L29 -> 25984 | N29: =M29 -> 25984 | O29: =N29 -> 25984 | P29: =O29 -> 25984
A30: Total Receivables | B30: 474 | C30: 505 | D30: 826 | E30: 1265 | F30: 1424 | G30: 1657 | H30: 2429 | I30: 4650 | J30: 3827 | K30: 9999 | L30: =L6*'Forecast Assumptions'!L12 -> 10722.272 | M30: =M6*'Forecast Assumptions'!M12 -> 12330.613 | N30: =N6*'Forecast Assumptions'!N12 -> 14796.735 | O30: =O6*'Forecast Assumptions'!O12 -> 18495.919 | P30: =P6*'Forecast Assumptions'!P12 -> 24044.695
A31: Inventory | B31: 483 | C31: 418 | D31: 794 | E31: 796 | F31: 1575 | G31: 979 | H31: 1826 | I31: 2605 | J31: 5159 | K31: 5282 | L31: =L6*'Forecast Assumptions'!L13 -> 6031.278 | M31: =M6*'Forecast Assumptions'!M13 -> 6935.9697 | N31: =N6*'Forecast Assumptions'!N13 -> 8323.1636 | O31: =O6*'Forecast Assumptions'!O13 -> 10403.955 | P31: =P6*'Forecast Assumptions'!P13 -> 13525.141
A32: Prepaid Expenses | B32: 70 | C32: 93 | D32: 118 | E32: 86 | F32: 136 | G32: 157 | H32: 239 | I32: 366 | J32: 791 | K32: 3080 | L32: =L6*'Forecast Assumptions'!L14 -> 3350.71 | M32: =M6*'Forecast Assumptions'!M14 -> 3853.3165 | N32: =N6*'Forecast Assumptions'!N14 -> 4623.9798 | O32: =O6*'Forecast Assumptions'!O14 -> 5779.9748 | P32: =P6*'Forecast Assumptions'!P14 -> 7513.9672
A33: Deferred Tax Assets Current | B33: 63 | C33: 0 | D33: 0 | E33: 0 | F33: 0 | G33: 0 | H33: 0 | I33: 0 | J33: 0 | K33: 0 | L33: 0 | M33: 0 | N33: 0 | O33: 0 | P33: 0
A34: Total Current Assets | B34: =B29+B30+B31+B32+B33 -> 5713 | C34: =C29+C30+C31+C32+C33 -> 6053 | D34: =D29+D30+D31+D32+D33 -> 8536 | E34: =E29+E30+E31+E32+E33 -> 9255 | F34: =F29+F30+F31+F32+F33 -> 10557 | G34: =G29+G30+G31+G32+G33 -> 13690 | H34: =H29+H30+H31+H32+H33 -> 16055 | I34: =I29+I30+I31+I32+I33 -> 28829 | ... K34: =K29+K30+K31+K32+K33 -> 44345 | L34: =SUM(L30:L33) -> 20104.26 | M34: =SUM(M30:M33) -> 23119.899 | N34: =SUM(N30:N33) -> 27743.879 | O34: =SUM(O30:O33) -> 34679.849 | P34: =SUM(P30:P33) -> 45083.803
A36: Surplus Cash | L36: =IF((L56+L66+L70)>(L34+L44),(L56+L66+L70)-(L34+L44),0) -> 7231618.2 | M36: =IF((M56+M66+M70)>(M34+M44),(M56+M66+M70)-(M34+M44),0) -> 14815327 | N36: =IF((N56+N66+N70)>(N34+N44),(N56+N66+N70)-(N34+N44),0) -> 18558194 | O36: =IF((O56+O66+O70)>(O34+O44),(O56+O66+O70)-(O34+O44),0) -> 27055605 | P36: =IF((P56+P66+P70)>(P34+P44),(P56+P66+P70)-(P34+P44),0) -> 27656861
A38: Net Property, Plant & Equipment | B38: 557 | C38: 466 | D38: 521 | E38: 997 | F38: 1404 | G38: 2292 | H38: 2856 | I38: 3607 | J38: 4845 | K38: 5260 | L38: =L6*'Forecast Assumptions'!L15 -> 12062.556 | M38: =M6*'Forecast Assumptions'!M15 -> 13871.939 | N38: =N6*'Forecast Assumptions'!N15 -> 16646.327 | O38: =O6*'Forecast Assumptions'!O15 -> 20807.909 | P38: =P6*'Forecast Assumptions'!P15 -> 27050.282
A39: Long-Term Investments | B39: 0 | C39: 0 | D39: 0 | E39: 0 | F39: 0 | G39: 77 | H39: 144 | I39: 266 | J39: 299 | K39: 1546 | L39: =K39 -> 1546 | M39: =L39 -> 1546 | N39: =M39 -> 1546 | O39: =N39 -> 1546 | P39: =O39 -> 1546
A40: Goodwill | B40: 618 | C40: 618 | D40: 618 | E40: 618 | F40: 618 | G40: 618 | H40: 4193 | I40: 4349 | J40: 4372 | K40: 4430 | L40: =K40 -> 4430 | M40: =L40 -> 4430 | N40: =M40 -> 4430 | O40: =N40 -> 4430 | P40: =O40 -> 4430
A41: Other Intangibles | B41: 222 | C41: 166 | D41: 104 | E41: 52 | F41: 45 | G41: 49 | H41: 2737 | I41: 2339 | J41: 1676 | K41: 1112 | L41: =K41 -> 1112 | M41: =L41 -> 1112 | N41: =M41 -> 1112 | O41: =N41 -> 1112 | P41: =O41 -> 1112
A42: Deferred Tax Assets | B42: 0 | C42: 0 | D42: 0 | E42: 245 | F42: 560 | G42: 548 | H42: 806 | I42: 1222 | J42: 3396 | K42: 6081 | L42: =K42 -> 6081 | M42: =L42 -> 6081 | N42: =M42 -> 6081 | O42: =N42 -> 6081 | P42: =O42 -> 6081
A43: Other Long-Term Assets | B43: 91 | C43: 67 | D43: 62 | E43: 74 | F43: 108 | G43: 41 | H43: 2000 | I43: 3575 | J43: 3521 | K43: 2954 | L43: =K43 -> 2954 | M43: =L43 -> 2954 | N43: =M43 -> 2954 | O43: =N43 -> 2954 | P43: =O43 -> 2954
A44: Total Long Term Assets | B44: =SUM(B38:B43) -> 1488 | C44: =SUM(C38:C43) -> 1317 | D44: =SUM(D38:D43) -> 1305 | E44: =SUM(E38:E43) -> 1986 | F44: =SUM(F38:F43) -> 2735 | G44: =SUM(G38:G43) -> 3625 | H44: =SUM(H38:H43) -> 12736 | I44: =SUM(I38:I43) -> 15358 | ... P44: =SUM(P38:P43) -> 43173.282
A46: Total Asets | B46: =B34+B44 -> 7201 | C46: =C34+C44 -> 7370 | D46: =D34+D44 -> 9841 | E46: =E34+E44 -> 11241 | F46: =F34+F44 -> 13292 | G46: =G34+G44 -> 17315 | H46: =H34+H44 -> 28791 | I46: =I34+I44 -> 44187 | ... K46: =K34+K44 -> 65728 | L46: =L34+L36+L44 -> 7279908 | M46: =M34+M36+M44 -> 14868442 | N46: =N34+N36+N44 -> 18618707 | O46: =O34+O36+O44 -> 27127216 | P46: =P34+P36+P44 -> 27745118
A49: Accounts Payable | B49: 293 | C49: 296 | D49: 485 | E49: 596 | F49: 511 | G49: 687 | H49: 1149 | I49: 1783 | J49: 1193 | K49: 2699 | L49: =L6/'Forecast Assumptions'!L17 -> 1340284 | M49: =M6/'Forecast Assumptions'!M17 -> 1926658.2 | N49: =N6/'Forecast Assumptions'!N17 -> 3082653.2 | O49: =O6/'Forecast Assumptions'!O17 -> 5779974.8 | P49: =P6/'Forecast Assumptions'!P17 -> 3756983.6
A50: Accrued Expenses | B50: 132 | C50: 106 | D50: 178 | E50: 224 | F50: 200 | G50: 223 | H50: 297 | I50: 409 | J50: 530 | K50: 675 | L50: =L6/'Forecast Assumptions'!L18 -> 1675355 | M50: =M6/'Forecast Assumptions'!M18 -> 2568877.7 | N50: =N6/'Forecast Assumptions'!N18 -> 3082653.2 | O50: =O6/'Forecast Assumptions'!O18 -> 3853316.5 | P50: =P6/'Forecast Assumptions'!P18 -> 5009311.5
A51: Current Portion of LT Debt | B51: 0 | C51: 1413 | D51: 796 | E51: 15 | F51: 0 | G51: 0 | H51: 999 | I51: 0 | J51: 1250 | K51: 1250 | L51: =K51 -> 1250 | M51: =L51 -> 1250 | N51: =M51 -> 1250 | O51: =N51 -> 1250 | P51: =O51 -> 1250
A52: Current Portion of Lease Obligations | B52: 0 | C52: 4 | D52: 4 | E52: 0 | F52: 0 | G52: 91 | H52: 0 | I52: 144 | J52: 176 | K52: 228 | L52: =K52 -> 228 | M52: =L52 -> 228 | N52: =M52 -> 228 | O52: =N52 -> 228 | P52: =O52 -> 228
A53: Current Income Taxes Payable | B53: 3 | C53: 2 | D53: 4 | E53: 33 | F53: 91 | G53: 61 | H53: 0 | I53: 132 | J53: 467 | K53: 296 | L53: =K53 -> 296 | M53: =L53 -> 296 | N53: =M53 -> 296 | O53: =N53 -> 296 | P53: =O53 -> 296
A54: Unearned Revenue, Current | B54: 296 | C54: 322 | D54: 85 | E54: 53 | F54: 92 | G54: 141 | H54: 288 | I54: 300 | J54: 354 | K54: 764 | L54: =L6/'Forecast Assumptions'!L19 -> 3350710 | M54: =M6/'Forecast Assumptions'!M19 -> 7706633 | N54: =N6/'Forecast Assumptions'!N19 -> 9247959.6 | O54: =O6/'Forecast Assumptions'!O19 -> 11559950 | P54: =P6/'Forecast Assumptions'!P19 -> 15027934
A55: Other Current Liabilities | B55: 172 | C55: 208 | D55: 236 | E55: 232 | F55: 435 | G55: 581 | H55: 1192 | I55: 1567 | J55: 2593 | K55: 4719 | L55: =L6/'Forecast Assumptions'!L20 -> 837677.5 | M55: =M6/'Forecast Assumptions'!M20 -> 2568877.7 | N55: =N6/'Forecast Assumptions'!N20 -> 3082653.2 | O55: =O6/'Forecast Assumptions'!O20 -> 5779974.8 | P55: =P6/'Forecast Assumptions'!P20 -> 3756983.6
A56: Total Current Liabilities | B56: =SUM(B49:B55) -> 896 | C56: =SUM(C49:C55) -> 2351 | D56: =SUM(D49:D55) -> 1788 | E56: =SUM(E49:E55) -> 1153 | F56: =SUM(F49:F55) -> 1329 | G56: =SUM(G49:G55) -> 1784 | H56: =SUM(H49:H55) -> 3925 | I56: =SUM(I49:I55) -> 4335 | ... P56: =SUM(P49:P55) -> 27552987
A58: Additional Funding Needed | L58: =IF((L34+L44)>(L56+L66+L70),(L34+L44)-(L56+L66+L70),0) -> 0 | M58: =IF((M34+M44)>(M56+M66+M70),(M34+M44)-(M56+M66+M70),0) -> 0 | N58: =IF((N34+N44)>(N56+N66+N70),(N34+N44)-(N56+N66+N70),0) -> 0 | O58: =IF((O34+O44)>(O56+O66+O70),(O34+O44)-(O56+O66+O70),0) -> 0 | P58: =IF((P34+P44)>(P56+P66+P70),(P34+P44)-(P56+P66+P70),0) -> 0
A60: Long-Term Debt | B60: 1384 | C60: 7 | D60: 1983 | E60: 1985 | F60: 1988 | G60: 1991 | H60: 5964 | I60: 10946 | J60: 9703 | K60: 8459 | L60: =K60 -> 8459 | M60: =L60 -> 8459 | N60: =M60 -> 8459 | O60: =N60 -> 8459 | P60: =O60 -> 8459
A61: Unearned Revenue Non-Current | B61: 108 | C61: 44 | D61: 4 | E61: 15 | F61: 46 | G61: 60 | H61: 163 | I61: 202 | J61: 218 | K61: 573 | L61: =K61 -> 573 | M61: =L61 -> 573 | N61: =M61 -> 573 | O61: =N61 -> 573 | P61: =O61 -> 573
A62: Pension & Other Post-Retire. Benefits | B62: 0 | C62: 0 | D62: 10 | E62: 12 | F62: 20 | G62: 22 | H62: 0 | I62: 0 | J62: 0 | K62: 0 | L62: =K62 -> 0 | M62: =L62 -> 0 | N62: =M62 -> 0 | O62: =N62 -> 0 | P62: =O62 -> 0
A63: Def. Tax Liability, Non-Curr. | B63: 232 | C63: 301 | D63: 141 | E63: 18 | F63: 19 | G63: 29 | H63: 241 | I63: 245 | J63: 247 | K63: 462 | L63: =K63 -> 462 | M63: =L63 -> 462 | N63: =M63 -> 462 | O63: =N63 -> 462 | P63: =O63 -> 462
A64: Capital Leases | B64: 14 | C64: 10 | D64: 0 | E64: 0 | F64: 0 | G64: 561 | H64: 634 | I64: 741 | J64: 902 | K64: 1119 | L64: =K64 -> 1119 | M64: =L64 -> 1119 | N64: =M64 -> 1119 | O64: =N64 -> 1119 | P64: =O64 -> 1119
A65: Other Non-Current Liabilities | B65: 149 | C65: 188 | D65: 153 | E65: 587 | F65: 548 | G65: 664 | H65: 971 | I65: 1106 | J65: 1448 | K65: 1506 | L65: =K65 -> 1506 | M65: =L65 -> 1506 | N65: =M65 -> 1506 | O65: =N65 -> 1506 | P65: =O65 -> 1506
A66: Total Long-Term Liabilities | B66: =SUM(B60:B65) -> 1887 | C66: =SUM(C60:C65) -> 550 | D66: =SUM(D60:D65) -> 2291 | E66: =SUM(E60:E65) -> 2617 | F66: =SUM(F60:F65) -> 2621 | G66: =SUM(G60:G65) -> 3327 | H66: =SUM(H60:H65) -> 7973 | I66: =SUM(I60:I65) -> 13240 | ... P66: =SUM(P60:P65) -> 12119
A68: Total Liabilities | B68: =B56+B66 -> 2783 | C68: =C56+C66 -> 2901 | D68: =D56+D66 -> 4079 | E68: =E56+E66 -> 3770 | F68: =F56+F66 -> 3950 | G68: =G56+G66 -> 5111 | H68: =H56+H66 -> 11898 | I68: =I56+I66 -> 17575 | ... K68: =K56+K66 -> 22750 | L68: =L56+L58+L66 -> 7217919.5 | M68: =M56+M58+M66 -> 14784940 | N68: =N56+N58+N66 -> 18509812 | O68: =O56+O58+O66 -> 26987108 | P68: =P56+P58+P66 -> 27565106
A70: Total Stockholders' Equity | B70: 4418 | C70: 4469 | D70: 5762 | E70: 7471 | F70: 9342 | G70: 12204 | H70: 16893 | I70: 26612 | J70: 22101 | K70: 42978 | L70: =K70+L21 -> 61988.536 | M70: =L70+M21 -> 83502.664 | N70: =M70+N21 -> 108894.85 | O70: =N70+O21 -> 140107.15 | P70: =O70+P21 -> 180012.23
A72: Total Liabilities And Equity | B72: =B68+B70 -> 7201 | C72: =C68+C70 -> 7370 | D72: =D68+D70 -> 9841 | E72: =E68+E70 -> 11241 | F72: =F68+F70 -> 13292 | G72: =G68+G70 -> 17315 | H72: =H68+H70 -> 28791 | I72: =I68+I70 -> 44187 | ... P72: =P68+P70 -> 27745118
A74: check | L74: =L46-L72 -> 0 | M74: =M46-M72 -> 0 | N74: =N46-N72 -> 0 | O74: =O46-O72 -> 0 | P74: =P46-P72 -> 0

Sheet Ratio Analysis
B2: Ratio Analysis
C3: 42005 | D3: 42370 | E3: 42736 | F3: 43101 | G3: 43466 | H3: 43831 | I3: 44197 | J3: 44562 | K3: 44927 | L3: 45292 | M3: 45658 | N3: 46023 | O3: 46388 | P3: 46753 | Q3: 47119
B4: Liquidity:
B5: Current ratio | C5: ='Financial Statements'!B34/'Financial Statements'!B56 -> 6.3761161 | D5: ='Financial Statements'!C34/'Financial Statements'!C56 -> 2.5746491 | E5: ='Financial Statements'!D34/'Financial Statements'!D56 -> 4.7740492 | F5: ='Financial Statements'!E34/'Financial Statements'!E56 -> 8.0268864 | G5: ='Financial Statements'!F34/'Financial Statements'!F56 -> 7.9435666 | H5: ='Financial Statements'!G34/'Financial Statements'!G56 -> 7.6737668 | I5: ='Financial Statements'!H34/'Financial Statements'!H56 -> 4.0904459 | J5: ='Financial Statements'!I34/'Financial Statements'!I56 -> 6.6502884 | ... Q5: ='Financial Statements'!P34/'Financial Statements'!P56 -> 0.0016362583
B7: Activity:
B8: Receivables turnover | C8: ='Financial Statements'!B6/'Financial Statements'!B30 -> 9.8776371 | D8: ='Financial Statements'!C6/'Financial Statements'!C30 -> 9.9207921 | E8: ='Financial Statements'!D6/'Financial Statements'!D30 -> 8.3656174 | F8: ='Financial Statements'!E6/'Financial Statements'!E30 -> 7.6790514 | G8: ='Financial Statements'!F6/'Financial Statements'!F30 -> 8.2275281 | H8: ='Financial Statements'!G6/'Financial Statements'!G30 -> 6.5890163 | I8: ='Financial Statements'!H6/'Financial Statements'!H30 -> 6.864965 | J8: ='Financial Statements'!I6/'Financial Statements'!I30 -> 5.787957 | ... Q8: ='Financial Statements'!P6/'Financial Statements'!P30 -> 6.25
B9: Average Receivables Collection Period | C9: ='Financial Statements'!B30/'Financial Statements'!B6*365 -> 36.952157 | D9: ='Financial Statements'!C30/'Financial Statements'!C6*365 -> 36.791417 | E9: ='Financial Statements'!D30/'Financial Statements'!D6*365 -> 43.63097 | F9: ='Financial Statements'!E30/'Financial Statements'!E6*365 -> 47.531913 | G9: ='Financial Statements'!F30/'Financial Statements'!F6*365 -> 44.363264 | H9: ='Financial Statements'!G30/'Financial Statements'!G6*365 -> 55.395219 | I9: ='Financial Statements'!H30/'Financial Statements'!H6*365 -> 53.168516 | J9: ='Financial Statements'!I30/'Financial Statements'!I6*365 -> 63.061975 | ... Q9: ='Financial Statements'!P30/'Financial Statements'!P6*365 -> 58.4
B10: Fixed asset turnover | C10: ='Financial Statements'!B6/'Financial Statements'!B38 -> 8.4057451 | D10: ='Financial Statements'!C6/'Financial Statements'!C38 -> 10.751073 | E10: ='Financial Statements'!D6/'Financial Statements'!D38 -> 13.262956 | F10: ='Financial Statements'!E6/'Financial Statements'!E38 -> 9.7432297 | G10: ='Financial Statements'!F6/'Financial Statements'!F38 -> 8.3447293 | H10: ='Financial Statements'!G6/'Financial Statements'!G38 -> 4.7635253 | I10: ='Financial Statements'!H6/'Financial Statements'!H38 -> 5.8385854 | J10: ='Financial Statements'!I6/'Financial Statements'!I38 -> 7.4616024 | ... Q10: ='Financial Statements'!P6/'Financial Statements'!P38 -> 5.5555556
B11: Total asset turnover | C11: ='Financial Statements'!B6/'Financial Statements'!B46 -> 0.65018747 | D11: ='Financial Statements'!C6/'Financial Statements'!C46 -> 0.6797829 | E11: ='Financial Statements'!D6/'Financial Statements'!D46 -> 0.70216441 | F11: ='Financial Statements'!E6/'Financial Statements'!E46 -> 0.86415799 | G11: ='Financial Statements'!F6/'Financial Statements'!F46 -> 0.88143244 | H11: ='Financial Statements'!G6/'Financial Statements'!G46 -> 0.63055154 | I11: ='Financial Statements'!H6/'Financial Statements'!H46 -> 0.57917405 | J11: ='Financial Statements'!I6/'Financial Statements'!I46 -> 0.60909317 | ... Q11: ='Financial Statements'!P6/'Financial Statements'!P46 -> 0.0054164247
B13: Debt Management:
B14: Debt Ratio | C14: ='Financial Statements'!B68/'Financial Statements'!B46 -> 0.3864741 | D14: ='Financial Statements'!C68/'Financial Statements'!C46 -> 0.3936228 | E14: ='Financial Statements'!D68/'Financial Statements'!D46 -> 0.4144904 | F14: ='Financial Statements'!E68/'Financial Statements'!E46 -> 0.33537941 | G14: ='Financial Statements'!F68/'Financial Statements'!F46 -> 0.29717123 | H14: ='Financial Statements'!G68/'Financial Statements'!G46 -> 0.29517759 | I14: ='Financial Statements'!H68/'Financial Statements'!H46 -> 0.41325414 | J14: ='Financial Statements'!I68/'Financial Statements'!I46 -> 0.39774142 | ... Q14: ='Financial Statements'!P68/'Financial Statements'!P46 -> 0.99351193
B16: Profitability:
B17: Gross margin | C17: ='Financial Statements'!B8/'Financial Statements'!B6 -> 0.55510466 | D17: ='Financial Statements'!C8/'Financial Statements'!C6 -> 0.56107784 | E17: ='Financial Statements'!D8/'Financial Statements'!D6 -> 0.58798842 | F17: ='Financial Statements'!E8/'Financial Statements'!E6 -> 0.59934116 | G17: ='Financial Statements'!F8/'Financial Statements'!F6 -> 0.61206897 | H17: ='Financial Statements'!G8/'Financial Statements'!G6 -> 0.61989375 | I17: ='Financial Statements'!H8/'Financial Statements'!H6 -> 0.63310345 | J17: ='Financial Statements'!I8/'Financial Statements'!I6 -> 0.64929033 | ... Q17: ='Financial Statements'!P8/'Financial Statements'!P6 -> 0.65
B18: Operating margin | C18: ='Financial Statements'!B13/'Financial Statements'!B6 -> 0.16211021 | D18: ='Financial Statements'!C13/'Financial Statements'!C6 -> 0.1752495 | E18: ='Financial Statements'!D13/'Financial Statements'!D6 -> 0.28031838 | F18: ='Financial Statements'!E13/'Financial Statements'!E6 -> 0.3304509 | G18: ='Financial Statements'!F13/'Financial Statements'!F6 -> 0.32468419 | H18: ='Financial Statements'!G13/'Financial Statements'!G6 -> 0.26067045 | I18: ='Financial Statements'!H13/'Financial Statements'!H6 -> 0.28311844 | J18: ='Financial Statements'!I13/'Financial Statements'!I6 -> 0.37307721 | ... Q18: ='Financial Statements'!P13/'Financial Statements'!P6 -> 0.35
B19: Profit margin on sales | C19: ='Financial Statements'!B21/'Financial Statements'!B6 -> 0.13477147 | D19: ='Financial Statements'!C21/'Financial Statements'!C6 -> 0.12255489 | E19: ='Financial Statements'!D21/'Financial Statements'!D6 -> 0.24109986 | F19: ='Financial Statements'!E21/'Financial Statements'!E6 -> 0.31367099 | G19: ='Financial Statements'!F21/'Financial Statements'!F6 -> 0.35344828 | H19: ='Financial Statements'!G21/'Financial Statements'!G6 -> 0.25609086 | I19: ='Financial Statements'!H21/'Financial Statements'!H6 -> 0.2597901 | J19: ='Financial Statements'!I21/'Financial Statements'!I6 -> 0.3623393 | ... Q19: ='Financial Statements'!P21/'Financial Statements'!P6 -> 0.26553934
B20: Return on assets | C20: ='Financial Statements'!B21/'Financial Statements'!B46 -> 0.087626719 | D20: ='Financial Statements'!C21/'Financial Statements'!C46 -> 0.083310719 | E20: ='Financial Statements'!D21/'Financial Statements'!D46 -> 0.16929174 | F20: ='Financial Statements'!E21/'Financial Statements'!E46 -> 0.27106129 | G20: ='Financial Statements'!F21/'Financial Statements'!F46 -> 0.31154078 | H20: ='Financial Statements'!G21/'Financial Statements'!G46 -> 0.16147849 | I20: ='Financial Statements'!H21/'Financial Statements'!H46 -> 0.15046369 | J20: ='Financial Statements'!I21/'Financial Statements'!I46 -> 0.2206984 | ... Q20: ='Financial Statements'!P21/'Financial Statements'!P46 -> 0.0014382738
B21: Return on equity | C21: ='Financial Statements'!B21/'Financial Statements'!B70 -> 0.14282481 | D21: ='Financial Statements'!C21/'Financial Statements'!C70 -> 0.13739092 | E21: ='Financial Statements'!D21/'Financial Statements'!D70 -> 0.28913572 | F21: ='Financial Statements'!E21/'Financial Statements'!E70 -> 0.40784366 | G21: ='Financial Statements'!F21/'Financial Statements'!F70 -> 0.44326697 | H21: ='Financial Statements'!G21/'Financial Statements'!G70 -> 0.22910521 | I21: ='Financial Statements'!H21/'Financial Statements'!H70 -> 0.25643758 | J21: ='Financial Statements'!I21/'Financial Statements'!I70 -> 0.36645123 | ... Q21: ='Financial Statements'!P21/'Financial Statements'!P70 -> 0.22167982
B22: All ratios calculated on year end figures
B25: Dupont Analysis
B26: Profit Margin on Sales | C26: ='Financial Statements'!B21/'Financial Statements'!B6 -> 0.13477147 | D26: ='Financial Statements'!C21/'Financial Statements'!C6 -> 0.12255489 | E26: ='Financial Statements'!D21/'Financial Statements'!D6 -> 0.24109986 | F26: ='Financial Statements'!E21/'Financial Statements'!E6 -> 0.31367099 | G26: ='Financial Statements'!F21/'Financial Statements'!F6 -> 0.35344828 | H26: ='Financial Statements'!G21/'Financial Statements'!G6 -> 0.25609086 | I26: ='Financial Statements'!H21/'Financial Statements'!H6 -> 0.2597901 | J26: ='Financial Statements'!I21/'Financial Statements'!I6 -> 0.3623393 | ... Q26: ='Financial Statements'!P21/'Financial Statements'!P6 -> 0.26553934
B27: Total Asset Turnover | C27: ='Financial Statements'!B6/'Financial Statements'!B46 -> 0.65018747 | D27: ='Financial Statements'!C6/'Financial Statements'!C46 -> 0.6797829 | E27: ='Financial Statements'!D6/'Financial Statements'!D46 -> 0.70216441 | F27: ='Financial Statements'!E6/'Financial Statements'!E46 -> 0.86415799 | G27: ='Financial Statements'!F6/'Financial Statements'!F46 -> 0.88143244 | H27: ='Financial Statements'!G6/'Financial Statements'!G46 -> 0.63055154 | I27: ='Financial Statements'!H6/'Financial Statements'!H46 -> 0.57917405 | J27: ='Financial Statements'!I6/'Financial Statements'!I46 -> 0.60909317 | ... Q27: ='Financial Statements'!P6/'Financial Statements'!P46 -> 0.0054164247
B28: Equity Multiplier | C28: ='Financial Statements'!B46/'Financial Statements'!B70 -> 1.629923 | D28: ='Financial Statements'!C46/'Financial Statements'!C70 -> 1.6491385 | E28: ='Financial Statements'!D46/'Financial Statements'!D70 -> 1.7079139 | F28: ='Financial Statements'!E46/'Financial Statements'!E70 -> 1.5046179 | G28: ='Financial Statements'!F46/'Financial Statements'!F70 -> 1.4228217 | H28: ='Financial Statements'!G46/'Financial Statements'!G70 -> 1.4187971 | I28: ='Financial Statements'!H46/'Financial Statements'!H70 -> 1.7043154 | J28: ='Financial Statements'!I46/'Financial Statements'!I70 -> 1.6604164 | ... Q28: ='Financial Statements'!P46/'Financial Statements'!P70 -> 154.12907
B30: ROE | C30: ='Financial Statements'!B21/'Financial Statements'!B70 -> 0.14282481 | D30: ='Financial Statements'!C21/'Financial Statements'!C70 -> 0.13739092 | E30: ='Financial Statements'!D21/'Financial Statements'!D70 -> 0.28913572 | F30: ='Financial Statements'!E21/'Financial Statements'!E70 -> 0.40784366 | G30: ='Financial Statements'!F21/'Financial Statements'!F70 -> 0.44326697 | H30: ='Financial Statements'!G21/'Financial Statements'!G70 -> 0.22910521 | I30: ='Financial Statements'!H21/'Financial Statements'!H70 -> 0.25643758 | J30: ='Financial Statements'!I21/'Financial Statements'!I70 -> 0.36645123 | ... Q30: ='Financial Statements'!P21/'Financial Statements'!P70 -> 0.22167982

Sheet Common-Size Statements
B1: 42005 | C1: 42370 | D1: 42736 | E1: 43101 | F1: 43466 | G1: 43831 | H1: 44197 | I1: 44562 | J1: 44927 | K1: 45292 | L1: 45658 | M1: 46023 | N1: 46388 | O1: 46753 | P1: 47119
A3: Revenues
A4: Total Revenues | B4: ='Financial Statements'!B6/'Financial Statements'!$B$6 -> 1 | C4: ='Financial Statements'!C6/'Financial Statements'!$C$6 -> 1 | D4: ='Financial Statements'!D6/'Financial Statements'!$D$6 -> 1 | E4: ='Financial Statements'!E6/'Financial Statements'!$E$6 -> 1 | F4: ='Financial Statements'!F6/'Financial Statements'!$F$6 -> 1 | G4: ='Financial Statements'!G6/'Financial Statements'!$G$6 -> 1 | H4: ='Financial Statements'!H6/'Financial Statements'!$H$6 -> 1 | I4: ='Financial Statements'!I6/'Financial Statements'!$I$6 -> 1 | J4: ='Financial Statements'!J6/'Financial Statements'!$J$6 -> 1 | K4: ='Financial Statements'!K6/'Financial Statements'!$K$6 -> 1 | L4: ='Financial Statements'!L6/'Financial Statements'!$L$6 -> 1 | M4: ='Financial Statements'!M6/'Financial Statements'!$M$6 -> 1 | N4: ='Financial Statements'!N6/'Financial Statements'!$N$6 -> 1 | O4: ='Financial Statements'!O6/'Financial Statements'!$O$6 -> 1 | P4: ='Financial Statements'!P6/'Financial Statements'!$P$6 -> 1
A5: Cost Of Revenues | B5: ='Financial Statements'!B7/'Financial Statements'!$B$6 -> 0.44489534 | C5: ='Financial Statements'!C7/'Financial Statements'!$C$6 -> 0.43892216 | D5: ='Financial Statements'!D7/'Financial Statements'!$D$6 -> 0.41201158 | E5: ='Financial Statements'!E7/'Financial Statements'!$E$6 -> 0.40065884 | F5: ='Financial Statements'!F7/'Financial Statements'!$F$6 -> 0.38793103 | G5: ='Financial Statements'!G7/'Financial Statements'!$G$6 -> 0.38010625 | H5: ='Financial Statements'!H7/'Financial Statements'!$H$6 -> 0.36689655 | I5: ='Financial Statements'!I7/'Financial Statements'!$I$6 -> 0.35070967 | J5: ='Financial Statements'!J7/'Financial Statements'!$J$6 -> 0.43071106 | K5: ='Financial Statements'!K7/'Financial Statements'!$K$6 -> 0.27282427 | L5: ='Financial Statements'!L7/'Financial Statements'!$L$6 -> 0.35 | M5: ='Financial Statements'!M7/'Financial Statements'!$M$6 -> 0.35 | N5: ='Financial Statements'!N7/'Financial Statements'!$N$6 -> 0.35 | O5: ='Financial Statements'!O7/'Financial Statements'!$O$6 -> 0.35 | P5: ='Financial Statements'!P7/'Financial Statements'!$P$6 -> 0.35
A6: Gross Profit | B6: ='Financial Statements'!B8/'Financial Statements'!$B$6 -> 0.55510466 | C6: ='Financial Statements'!C8/'Financial Statements'!$C$6 -> 0.56107784 | D6: ='Financial Statements'!D8/'Financial Statements'!$D$6 -> 0.58798842 | E6: ='Financial Statements'!E8/'Financial Statements'!$E$6 -> 0.59934116 | F6: ='Financial Statements'!F8/'Financial Statements'!$F$6 -> 0.61206897 | G6: ='Financial Statements'!G8/'Financial Statements'!$G$6 -> 0.61989375 | H6: ='Financial Statements'!H8/'Financial Statements'!$H$6 -> 0.63310345 | I6: ='Financial Statements'!I8/'Financial Statements'!$I$6 -> 0.64929033 | J6: ='Financial Statements'!J8/'Financial Statements'!$J$6 -> 0.56928894 | K6: ='Financial Statements'!K8/'Financial Statements'!$K$6 -> 0.72717573 | L6: ='Financial Statements'!L8/'Financial Statements'!$L$6 -> 0.65 | M6: ='Financial Statements'!M8/'Financial Statements'!$M$6 -> 0.65 | N6: ='Financial Statements'!N8/'Financial Statements'!$N$6 -> 0.65 | O6: ='Financial Statements'!O8/'Financial Statements'!$O$6 -> 0.65 | P6: ='Financial Statements'!P8/'Financial Statements'!$P$6 -> 0.65
A7: Operating Expenses & Income | C7: ='Financial Statements'!C9/'Financial Statements'!$C$6 -> 0 | D7: ='Financial Statements'!D9/'Financial Statements'!$D$6 -> 0 | E7: ='Financial Statements'!E9/'Financial Statements'!$E$6 -> 0 | F7: ='Financial Statements'!F9/'Financial Statements'!$F$6 -> 0 | G7: ='Financial Statements'!G9/'Financial Statements'!$G$6 -> 0 | H7: ='Financial Statements'!H9/'Financial Statements'!$H$6 -> 0 | I7: ='Financial Statements'!I9/'Financial Statements'!$I$6 -> 0 | J7: ='Financial Statements'!J9/'Financial Statements'!$J$6 -> 0 | K7: ='Financial Statements'!K9/'Financial Statements'!$K$6 -> 0 | L7: ='Financial Statements'!L9/'Financial Statements'!$L$6 -> 0 | M7: ='Financial Statements'!M9/'Financial Statements'!$M$6 -> 0 | N7: ='Financial Statements'!N9/'Financial Statements'!$N$6 -> 0 | O7: ='Financial Statements'!O9/'Financial Statements'!$O$6 -> 0 | P7: ='Financial Statements'!P9/'Financial Statements'!$P$6 -> 0
A8: Selling General & Admin Expenses | B8: ='Financial Statements'!B10/'Financial Statements'!$B$6 -> 0.10252029 | C8: ='Financial Statements'!C10/'Financial Statements'!$C$6 -> 0.12015968 | D8: ='Financial Statements'!D10/'Financial Statements'!$D$6 -> 0.095947902 | E8: ='Financial Statements'!E10/'Financial Statements'!$E$6 -> 0.083899526 | F8: ='Financial Statements'!F10/'Financial Statements'!$F$6 -> 0.084585183 | G8: ='Financial Statements'!G10/'Financial Statements'!$G$6 -> 0.10010991 | H8: ='Financial Statements'!H10/'Financial Statements'!$H$6 -> 0.11466267 | I8: ='Financial Statements'!I10/'Financial Statements'!$I$6 -> 0.080478561 | J8: ='Financial Statements'!J10/'Financial Statements'!$J$6 -> 0.090457478 | K8: ='Financial Statements'!K10/'Financial Statements'!$K$6 -> 0.043563901 | L8: ='Financial Statements'!L10/'Financial Statements'!$L$6 -> 0.1 | M8: ='Financial Statements'!M10/'Financial Statements'!$M$6 -> 0.1 | N8: ='Financial Statements'!N10/'Financial Statements'!$N$6 -> 0.1 | O8: ='Financial Statements'!O10/'Financial Statements'!$O$6 -> 0.1 | P8: ='Financial Statements'!P10/'Financial Statements'!$P$6 -> 0.1
A9: R&D Expenses | B9: ='Financial Statements'!B11/'Financial Statements'!$B$6 -> 0.29047416 | C9: ='Financial Statements'!C11/'Financial Statements'!$C$6 -> 0.26566866 | D9: ='Financial Statements'!D11/'Financial Statements'!$D$6 -> 0.21172214 | E9: ='Financial Statements'!E11/'Financial Statements'!$E$6 -> 0.18499074 | F9: ='Financial Statements'!F11/'Financial Statements'!$F$6 -> 0.20279959 | G9: ='Financial Statements'!G11/'Financial Statements'!$G$6 -> 0.25911339 | H9: ='Financial Statements'!H11/'Financial Statements'!$H$6 -> 0.23532234 | I9: ='Financial Statements'!I11/'Financial Statements'!$I$6 -> 0.19573456 | J9: ='Financial Statements'!J11/'Financial Statements'!$J$6 -> 0.27207681 | K9: ='Financial Statements'!K11/'Financial Statements'!$K$6 -> 0.14239519 | L9: ='Financial Statements'!L11/'Financial Statements'!$L$6 -> 0.2 | M9: ='Financial Statements'!M11/'Financial Statements'!$M$6 -> 0.2 | N9: ='Financial Statements'!N11/'Financial Statements'!$N$6 -> 0.2 | O9: ='Financial Statements'!O11/'Financial Statements'!$O$6 -> 0.2 | P9: ='Financial Statements'!P11/'Financial Statements'!$P$6 -> 0.2
A10: Total Operating Expenses | B10: ='Financial Statements'!B12/'Financial Statements'!$B$6 -> 0.39299445 | C10: ='Financial Statements'!C12/'Financial Statements'!$C$6 -> 0.38582834 | D10: ='Financial Statements'!D12/'Financial Statements'!$D$6 -> 0.30767004 | E10: ='Financial Statements'!E12/'Financial Statements'!$E$6 -> 0.26889026 | F10: ='Financial Statements'!F12/'Financial Statements'!$F$6 -> 0.28738477 | G10: ='Financial Statements'!G12/'Financial Statements'!$G$6 -> 0.3592233 | H10: ='Financial Statements'!H12/'Financial Statements'!$H$6 -> 0.34998501 | I10: ='Financial Statements'!I12/'Financial Statements'!$I$6 -> 0.27621312 | J10: ='Financial Statements'!J12/'Financial Statements'!$J$6 -> 0.36253429 | K10: ='Financial Statements'!K12/'Financial Statements'!$K$6 -> 0.1859591 | L10: ='Financial Statements'!L12/'Financial Statements'!$L$6 -> 0.3 | M10: ='Financial Statements'!M12/'Financial Statements'!$M$6 -> 0.3 | N10: ='Financial Statements'!N12/'Financial Statements'!$N$6 -> 0.3 | O10: ='Financial Statements'!O12/'Financial Statements'!$O$6 -> 0.3 | P10: ='Financial Statements'!P12/'Financial Statements'!$P$6 -> 0.3
A12: Operating Income | B12: ='Financial Statements'!B13/'Financial Statements'!$B$6 -> 0.16211021 | C12: ='Financial Statements'!C13/'Financial Statements'!$C$6 -> 0.1752495 | D12: ='Financial Statements'!D13/'Financial Statements'!$D$6 -> 0.28031838 | E12: ='Financial Statements'!E13/'Financial Statements'!$E$6 -> 0.3304509 | F12: ='Financial Statements'!F13/'Financial Statements'!$F$6 -> 0.32468419 | G12: ='Financial Statements'!G13/'Financial Statements'!$G$6 -> 0.26067045 | H12: ='Financial Statements'!H13/'Financial Statements'!$H$6 -> 0.28311844 | I12: ='Financial Statements'!I13/'Financial Statements'!$I$6 -> 0.37307721 | J12: ='Financial Statements'!J13/'Financial Statements'!$J$6 -> 0.20675465 | K12: ='Financial Statements'!K13/'Financial Statements'!$K$6 -> 0.54121664 | L12: ='Financial Statements'!L13/'Financial Statements'!$L$6 -> 0.35 | M12: ='Financial Statements'!M13/'Financial Statements'!$M$6 -> 0.35 | N12: ='Financial Statements'!N13/'Financial Statements'!$N$6 -> 0.35 | O12: ='Financial Statements'!O13/'Financial Statements'!$O$6 -> 0.35 | P12: ='Financial Statements'!P13/'Financial Statements'!$P$6 -> 0.35
A13: Earnings from Continuing Operations | B13: ='Financial Statements'!B14/'Financial Statements'!$B$6 -> 0 | C13: ='Financial Statements'!C14/'Financial Statements'!$C$6 -> 0 | D13: ='Financial Statements'!D14/'Financial Statements'!$D$6 -> 0 | E13: ='Financial Statements'!E14/'Financial Statements'!$E$6 -> 0 | F13: ='Financial Statements'!F14/'Financial Statements'!$F$6 -> 0 | G13: ='Financial Statements'!G14/'Financial Statements'!$G$6 -> 0 | H13: ='Financial Statements'!H14/'Financial Statements'!$H$6 -> 0 | I13: ='Financial Statements'!I14/'Financial Statements'!$I$6 -> 0 | J13: ='Financial Statements'!J14/'Financial Statements'!$J$6 -> 0 | K13: ='Financial Statements'!K14/'Financial Statements'!$K$6 -> 0 | L13: ='Financial Statements'!L14/'Financial Statements'!$L$6 -> 0 | M13: ='Financial Statements'!M14/'Financial Statements'!$M$6 -> 0 | N13: ='Financial Statements'!N14/'Financial Statements'!$N$6 -> 0 | O13: ='Financial Statements'!O14/'Financial Statements'!$O$6 -> 0 | P13: ='Financial Statements'!P14/'Financial Statements'!$P$6 -> 0
A14: Interest Expense | B14: ='Financial Statements'!B15/'Financial Statements'!$B$6 -> -0.0098248612 | C14: ='Financial Statements'!C15/'Financial Statements'!$C$6 -> -0.0093812375 | D14: ='Financial Statements'!D15/'Financial Statements'!$D$6 -> -0.0083936324 | E14: ='Financial Statements'!E15/'Financial Statements'!$E$6 -> -0.0062795965 | F14: ='Financial Statements'!F15/'Financial Statements'!$F$6 -> -0.004950495 | G14: ='Financial Statements'!G15/'Financial Statements'!$G$6 -> -0.0047627771 | H14: ='Financial Statements'!H15/'Financial Statements'!$H$6 -> -0.011034483 | I14: ='Financial Statements'!I15/'Financial Statements'!$I$6 -> -0.0087686706 | J14: ='Financial Statements'!J15/'Financial Statements'!$J$6 -> -0.009713057 | K14: ='Financial Statements'!K15/'Financial Statements'!$K$6 -> -0.0042185089 | L14: ='Financial Statements'!L15/'Financial Statements'!$L$6 -> -0.0038350081 | M14: ='Financial Statements'!M15/'Financial Statements'!$M$6 -> -0.0033347897 | N14: ='Financial Statements'!N15/'Financial Statements'!$N$6 -> -0.0027789914 | O14: ='Financial Statements'!O15/'Financial Statements'!$O$6 -> -0.0022231931 | P14: ='Financial Statements'!P15/'Financial Statements'!$P$6 -> -0.0017101485
A15: Interest And Investment Income | B15: ='Financial Statements'!B16/'Financial Statements'!$B$6 -> 0.0059803503 | C15: ='Financial Statements'!C16/'Financial Statements'!$C$6 -> 0.0077844311 | D15: ='Financial Statements'!D16/'Financial Statements'!$D$6 -> 0.0078147612 | E15: ='Financial Statements'!E16/'Financial Statements'!$E$6 -> 0.0071031501 | F15: ='Financial Statements'!F16/'Financial Statements'!$F$6 -> 0.011608057 | G15: ='Financial Statements'!G16/'Financial Statements'!$G$6 -> 0.016303352 | H15: ='Financial Statements'!H16/'Financial Statements'!$H$6 -> 0.0034182909 | I15: ='Financial Statements'!I16/'Financial Statements'!$I$6 -> 0.0010775061 | J15: ='Financial Statements'!J16/'Financial Statements'!$J$6 -> 0.0098984207 | K15: ='Financial Statements'!K16/'Financial Statements'!$K$6 -> 0.014214898 | L15: ='Financial Statements'!L16/'Financial Statements'!$L$6 -> 0.012922634 | M15: ='Financial Statements'!M16/'Financial Statements'!$M$6 -> 0.011237073 | N15: ='Financial Statements'!N16/'Financial Statements'!$N$6 -> 0.0093642278 | O15: ='Financial Statements'!O16/'Financial Statements'!$O$6 -> 0.0074913822 | P15: ='Financial Statements'!P16/'Financial Statements'!$P$6 -> 0.0057626017
A16: Net Interest Expenses | B16: ='Financial Statements'!B17/'Financial Statements'!$B$6 -> -0.0038445109 | C16: ='Financial Statements'!C17/'Financial Statements'!$C$6 -> -0.0015968064 | D16: ='Financial Statements'!D17/'Financial Statements'!$D$6 -> -0.0005788712 | E16: ='Financial Statements'!E17/'Financial Statements'!$E$6 -> 0.00082355363 | F16: ='Financial Statements'!F17/'Financial Statements'!$F$6 -> 0.0066575623 | G16: ='Financial Statements'!G17/'Financial Statements'!$G$6 -> 0.011540575 | H16: ='Financial Statements'!H17/'Financial Statements'!$H$6 -> -0.0076161919 | I16: ='Financial Statements'!I17/'Financial Statements'!$I$6 -> -0.0076911644 | J16: ='Financial Statements'!J17/'Financial Statements'!$J$6 -> 0.00018536368 | K16: ='Financial Statements'!K17/'Financial Statements'!$K$6 -> 0.0099963888 | L16: ='Financial Statements'!L17/'Financial Statements'!$L$6 -> 0.0090876262 | M16: ='Financial Statements'!M17/'Financial Statements'!$M$6 -> 0.0079022837 | N16: ='Financial Statements'!N17/'Financial Statements'!$N$6 -> 0.0065852364 | O16: ='Financial Statements'!O17/'Financial Statements'!$O$6 -> 0.0052681891 | P16: ='Financial Statements'!P17/'Financial Statements'!$P$6 -> 0.0040524532
A17: Other Non Operating Income (Expenses) | B17: ='Financial Statements'!B18/'Financial Statements'!$B$6 -> 0.0029901751 | C17: ='Financial Statements'!C18/'Financial Statements'!$C$6 -> 0.00079840319 | D17: ='Financial Statements'!D18/'Financial Statements'!$D$6 -> -0.0005788712 | E17: ='Financial Statements'!E18/'Financial Statements'!$E$6 -> -0.0022647725 | F17: ='Financial Statements'!F18/'Financial Statements'!$F$6 -> 0.0011949471 | G17: ='Financial Statements'!G18/'Financial Statements'!$G$6 -> 0 | H17: ='Financial Statements'!H18/'Financial Statements'!$H$6 -> 0.00023988006 | I17: ='Financial Statements'!I18/'Financial Statements'!$I$6 -> 0.00026008769 | J17: ='Financial Statements'!J18/'Financial Statements'!$J$6 -> -0.00011121821 | K17: ='Financial Statements'!K18/'Financial Statements'!$K$6 -> -1.6414432e-05 | L17: ='Financial Statements'!L18/'Financial Statements'!$L$6 -> 0 | M17: ='Financial Statements'!M18/'Financial Statements'!$M$6 -> 0 | N17: ='Financial Statements'!N18/'Financial Statements'!$N$6 -> 0 | O17: ='Financial Statements'!O18/'Financial Statements'!$O$6 -> 0 | P17: ='Financial Statements'!P18/'Financial Statements'!$P$6 -> 0
A18: EBT, Incl. Unusual Items | B18: ='Financial Statements'!B19/'Financial Statements'!$B$6 -> 0.16125587 | C18: ='Financial Statements'!C19/'Financial Statements'!$C$6 -> 0.1744511 | D18: ='Financial Statements'!D19/'Financial Statements'!$D$6 -> 0.27916064 | E18: ='Financial Statements'!E19/'Financial Statements'!$E$6 -> 0.32900968 | F18: ='Financial Statements'!F19/'Financial Statements'!$F$6 -> 0.3325367 | G18: ='Financial Statements'!G19/'Financial Statements'!$G$6 -> 0.27221103 | H18: ='Financial Statements'!H19/'Financial Statements'!$H$6 -> 0.27574213 | I18: ='Financial Statements'!I19/'Financial Statements'!$I$6 -> 0.36564613 | J18: ='Financial Statements'!J19/'Financial Statements'!$J$6 -> 0.2068288 | K18: ='Financial Statements'!K19/'Financial Statements'!$K$6 -> 0.55119661 | L18: ='Financial Statements'!L19/'Financial Statements'!$L$6 -> 0.35908763 | M18: ='Financial Statements'!M19/'Financial Statements'!$M$6 -> 0.35790228 | N18: ='Financial Statements'!N19/'Financial Statements'!$N$6 -> 0.35658524 | O18: ='Financial Statements'!O19/'Financial Statements'!$O$6 -> 0.35526819 | P18: ='Financial Statements'!P19/'Financial Statements'!$P$6 -> 0.35405245
A19: Income Tax Expense | B19: ='Financial Statements'!B20/'Financial Statements'!$B$6 -> 0.026484408 | C19: ='Financial Statements'!C20/'Financial Statements'!$C$6 -> 0.051896208 | D19: ='Financial Statements'!D20/'Financial Statements'!$D$6 -> 0.038060781 | E19: ='Financial Statements'!E20/'Financial Statements'!$E$6 -> 0.015338686 | F19: ='Financial Statements'!F20/'Financial Statements'!$F$6 -> -0.020911574 | G19: ='Financial Statements'!G20/'Financial Statements'!$G$6 -> 0.016120169 | H19: ='Financial Statements'!H20/'Financial Statements'!$H$6 -> 0.015952024 | I19: ='Financial Statements'!I20/'Financial Statements'!$I$6 -> 0.0033068292 | J19: ='Financial Statements'!J20/'Financial Statements'!$J$6 -> 0.044895084 | K19: ='Financial Statements'!K20/'Financial Statements'!$K$6 -> 0.062703129 | L19: ='Financial Statements'!L20/'Financial Statements'!$L$6 -> 0.075408402 | M19: ='Financial Statements'!M20/'Financial Statements'!$M$6 -> 0.078738502 | N19: ='Financial Statements'!N20/'Financial Statements'!$N$6 -> 0.082014604 | O19: ='Financial Statements'!O20/'Financial Statements'!$O$6 -> 0.085264365 | P19: ='Financial Statements'!P20/'Financial Statements'!$P$6 -> 0.088513113
A20: Net Income | B20: ='Financial Statements'!B21/'Financial Statements'!$B$6 -> 0.13477147 | C20: ='Financial Statements'!C21/'Financial Statements'!$C$6 -> 0.12255489 | D20: ='Financial Statements'!D21/'Financial Statements'!$D$6 -> 0.24109986 | E20: ='Financial Statements'!E21/'Financial Statements'!$E$6 -> 0.31367099 | F20: ='Financial Statements'!F21/'Financial Statements'!$F$6 -> 0.35344828 | G20: ='Financial Statements'!G21/'Financial Statements'!$G$6 -> 0.25609086 | H20: ='Financial Statements'!H21/'Financial Statements'!$H$6 -> 0.2597901 | I20: ='Financial Statements'!I21/'Financial Statements'!$I$6 -> 0.3623393 | J20: ='Financial Statements'!J21/'Financial Statements'!$J$6 -> 0.16193371 | K20: ='Financial Statements'!K21/'Financial Statements'!$K$6 -> 0.48849348 | L20: ='Financial Statements'!L21/'Financial Statements'!$L$6 -> 0.28367922 | M20: ='Financial Statements'!M21/'Financial Statements'!$M$6 -> 0.27916378 | N20: ='Financial Statements'!N21/'Financial Statements'!$N$6 -> 0.27457063 | O20: ='Financial Statements'!O21/'Financial Statements'!$O$6 -> 0.27000382 | P20: ='Financial Statements'!P21/'Financial Statements'!$P$6 -> 0.26553934
B26: 42005 | C26: 42370 | D26: 42736 | E26: 43101 | F26: 43466 | G26: 43831 | H26: 44197 | I26: 44562 | J26: 44927 | K26: 45292 | L26: 45658 | M26: 46023 | N26: 46388 | O26: 46753 | P26: 47119
A28: Total Cash & ST Investments | B28: ='Financial Statements'!B29/'Financial Statements'!$B$46 -> 0.64199417 | C28: ='Financial Statements'!C29/'Financial Statements'!$C$46 -> 0.6834464 | D28: ='Financial Statements'!D29/'Financial Statements'!$D$46 -> 0.69078346 | E28: ='Financial Statements'!E29/'Financial Statements'!$E$46 -> 0.63232808 | F28: ='Financial Statements'!F29/'Financial Statements'!$F$46 -> 0.55838098 | G28: ='Financial Statements'!G29/'Financial Statements'!$G$46 -> 0.62933872 | H28: ='Financial Statements'!H29/'Financial Statements'!$H$46 -> 0.4015491 | I28: ='Financial Statements'!I29/'Financial Statements'!$I$46 -> 0.47996017 | J28: ='Financial Statements'!J29/'Financial Statements'!$J$46 -> 0.3228595 | K28: ='Financial Statements'!K29/'Financial Statements'!$K$46 -> 0.39532619 | L28: ='Financial Statements'!L29/'Financial Statements'!$L$46 -> 0.0035692759 | M28: ='Financial Statements'!M29/'Financial Statements'!$M$46 -> 0.001747594 | N28: ='Financial Statements'!N29/'Financial Statements'!$N$46 -> 0.0013955856 | O28: ='Financial Statements'!O29/'Financial Statements'!$O$46 -> 0.00095785724 | P28: ='Financial Statements'!P29/'Financial Statements'!$P$46 -> 0.00093652511
A29: Total Receivables | B29: ='Financial Statements'!B30/'Financial Statements'!$B$46 -> 0.065824191 | C29: ='Financial Statements'!C30/'Financial Statements'!$C$46 -> 0.068521031 | D29: ='Financial Statements'!D30/'Financial Statements'!$D$46 -> 0.083934559 | E29: ='Financial Statements'!E30/'Financial Statements'!$E$46 -> 0.11253447 | F29: ='Financial Statements'!F30/'Financial Statements'!$F$46 -> 0.10713211 | G29: ='Financial Statements'!G30/'Financial Statements'!$G$46 -> 0.095697372 | H29: ='Financial Statements'!H30/'Financial Statements'!$H$46 -> 0.084366642 | I29: ='Financial Statements'!I30/'Financial Statements'!$I$46 -> 0.10523457 | J29: ='Financial Statements'!J30/'Financial Statements'!$J$46 -> 0.09292895 | K29: ='Financial Statements'!K30/'Financial Statements'!$K$46 -> 0.15212695 | L29: ='Financial Statements'!L30/'Financial Statements'!$L$46 -> 0.0014728582 | M29: ='Financial Statements'!M30/'Financial Statements'!$M$46 -> 0.00082931437 | N29: ='Financial Statements'!N30/'Financial Statements'!$N$46 -> 0.00079472411 | O29: ='Financial Statements'!O30/'Financial Statements'!$O$46 -> 0.00068182151 | P29: ='Financial Statements'!P30/'Financial Statements'!$P$46 -> 0.00086662795
A30: Inventory | B30: ='Financial Statements'!B31/'Financial Statements'!$B$46 -> 0.067074017 | C30: ='Financial Statements'!C31/'Financial Statements'!$C$46 -> 0.056716418 | D30: ='Financial Statements'!D31/'Financial Statements'!$D$46 -> 0.080682857 | E30: ='Financial Statements'!E31/'Financial Statements'!$E$46 -> 0.070812205 | F30: ='Financial Statements'!F31/'Financial Statements'!$F$46 -> 0.11849233 | G30: ='Financial Statements'!G31/'Financial Statements'!$G$46 -> 0.056540572 | H30: ='Financial Statements'!H31/'Financial Statements'!$H$46 -> 0.063422597 | I30: ='Financial Statements'!I31/'Financial Statements'!$I$46 -> 0.058953991 | J30: ='Financial Statements'!J31/'Financial Statements'!$J$46 -> 0.12527318 | K30: ='Financial Statements'!K31/'Financial Statements'!$K$46 -> 0.08036149 | L30: ='Financial Statements'!L31/'Financial Statements'!$L$46 -> 0.00082848272 | M30: ='Financial Statements'!M31/'Financial Statements'!$M$46 -> 0.00046648933 | N30: ='Financial Statements'!N31/'Financial Statements'!$N$46 -> 0.00044703231 | O30: ='Financial Statements'!O31/'Financial Statements'!$O$46 -> 0.0003835246 | P30: ='Financial Statements'!P31/'Financial Statements'!$P$46 -> 0.00048747822
A31: Prepaid Expenses | B31: ='Financial Statements'!B32/'Financial Statements'!$B$46 -> 0.0097208721 | C31: ='Financial Statements'!C32/'Financial Statements'!$C$46 -> 0.012618725 | D31: ='Financial Statements'!D32/'Financial Statements'!$D$46 -> 0.011990651 | E31: ='Financial Statements'!E32/'Financial Statements'!$E$46 -> 0.0076505649 | F31: ='Financial Statements'!F32/'Financial Statements'!$F$46 -> 0.010231718 | G31: ='Financial Statements'!G32/'Financial Statements'!$G$46 -> 0.0090672827 | H31: ='Financial Statements'!H32/'Financial Statements'!$H$46 -> 0.0083012052 | I31: ='Financial Statements'!I32/'Financial Statements'!$I$46 -> 0.0082829792 | J31: ='Financial Statements'!J32/'Financial Statements'!$J$46 -> 0.019207421 | K31: ='Financial Statements'!K32/'Financial Statements'!$K$46 -> 0.046859786 | L31: ='Financial Statements'!L32/'Financial Statements'!$L$46 -> 0.00046026818 | M31: ='Financial Statements'!M32/'Financial Statements'!$M$46 -> 0.00025916074 | N31: ='Financial Statements'!N32/'Financial Statements'!$N$46 -> 0.00024835128 | O31: ='Financial Statements'!O32/'Financial Statements'!$O$46 -> 0.00021306922 | P31: ='Financial Statements'!P32/'Financial Statements'!$P$46 -> 0.00027082123
A32: Deferred Tax Assets Current | B32: ='Financial Statements'!B33/'Financial Statements'!$B$46 -> 0.0087487849 | C32: ='Financial Statements'!C33/'Financial Statements'!$C$46 -> 0 | D32: ='Financial Statements'!D33/'Financial Statements'!$D$46 -> 0 | E32: ='Financial Statements'!E33/'Financial Statements'!$E$46 -> 0 | F32: ='Financial Statements'!F33/'Financial Statements'!$F$46 -> 0 | G32: ='Financial Statements'!G33/'Financial Statements'!$G$46 -> 0 | H32: ='Financial Statements'!H33/'Financial Statements'!$H$46 -> 0 | I32: ='Financial Statements'!I33/'Financial Statements'!$I$46 -> 0 | J32: ='Financial Statements'!J33/'Financial Statements'!$J$46 -> 0 | K32: ='Financial Statements'!K33/'Financial Statements'!$K$46 -> 0 | L32: ='Financial Statements'!L33/'Financial Statements'!$L$46 -> 0 | M32: ='Financial Statements'!M33/'Financial Statements'!$M$46 -> 0 | N32: ='Financial Statements'!N33/'Financial Statements'!$N$46 -> 0 | O32: ='Financial Statements'!O33/'Financial Statements'!$O$46 -> 0 | P32: ='Financial Statements'!P33/'Financial Statements'!$P$46 -> 0
A33: Total Current Assets | B33: ='Financial Statements'!B34/'Financial Statements'!$B$46 -> 0.79336203 | C33: ='Financial Statements'!C34/'Financial Statements'!$C$46 -> 0.82130258 | D33: ='Financial Statements'!D34/'Financial Statements'!$D$46 -> 0.86739153 | E33: ='Financial Statements'!E34/'Financial Statements'!$E$46 -> 0.82332533 | F33: ='Financial Statements'!F34/'Financial Statements'!$F$46 -> 0.79423714 | G33: ='Financial Statements'!G34/'Financial Statements'!$G$46 -> 0.79064395 | H33: ='Financial Statements'!H34/'Financial Statements'!$H$46 -> 0.55763954 | I33: ='Financial Statements'!I34/'Financial Statements'!$I$46 -> 0.65243171 | J33: ='Financial Statements'!J34/'Financial Statements'!$J$46 -> 0.56026905 | K33: ='Financial Statements'!K34/'Financial Statements'!$K$46 -> 0.67467442 | L33: ='Financial Statements'!L34/'Financial Statements'!$L$46 -> 0.0027616091 | M33: ='Financial Statements'!M34/'Financial Statements'!$M$46 -> 0.0015549644 | N33: ='Financial Statements'!N34/'Financial Statements'!$N$46 -> 0.0014901077 | O33: ='Financial Statements'!O34/'Financial Statements'!$O$46 -> 0.0012784153 | P33: ='Financial Statements'!P34/'Financial Statements'!$P$46 -> 0.0016249274
L34: ='Financial Statements'!L35/'Financial Statements'!$L$46 -> 0 | M34: ='Financial Statements'!M35/'Financial Statements'!$M$46 -> 0 | N34: ='Financial Statements'!N35/'Financial Statements'!$N$46 -> 0 | O34: ='Financial Statements'!O35/'Financial Statements'!$O$46 -> 0 | P34: ='Financial Statements'!P35/'Financial Statements'!$P$46 -> 0
A35: Surplus Cash | B35: ='Financial Statements'!B36/'Financial Statements'!$B$46 -> 0 | C35: ='Financial Statements'!C36/'Financial Statements'!$C$46 -> 0 | D35: ='Financial Statements'!D36/'Financial Statements'!$D$46 -> 0 | E35: ='Financial Statements'!E36/'Financial Statements'!$E$46 -> 0 | F35: ='Financial Statements'!F36/'Financial Statements'!$F$46 -> 0 | G35: ='Financial Statements'!G36/'Financial Statements'!$G$46 -> 0 | H35: ='Financial Statements'!H36/'Financial Statements'!$H$46 -> 0 | I35: ='Financial Statements'!I36/'Financial Statements'!$I$46 -> 0 | J35: ='Financial Statements'!J36/'Financial Statements'!$J$46 -> 0 | K35: ='Financial Statements'!K36/'Financial Statements'!$K$46 -> 0 | L35: ='Financial Statements'!L36/'Financial Statements'!$L$46 -> 0.9933667 | M35: ='Financial Statements'!M36/'Financial Statements'!$M$46 -> 0.99642768 | N35: ='Financial Statements'!N36/'Financial Statements'!$N$46 -> 0.99674987 | O35: ='Financial Statements'!O36/'Financial Statements'!$O$46 -> 0.99736019 | P35: ='Financial Statements'!P36/'Financial Statements'!$P$46 -> 0.996819
L36: ='Financial Statements'!L37/'Financial Statements'!$L$46 -> 0 | M36: ='Financial Statements'!M37/'Financial Statements'!$M$46 -> 0 | N36: ='Financial Statements'!N37/'Financial Statements'!$N$46 -> 0 | O36: ='Financial Statements'!O37/'Financial Statements'!$O$46 -> 0 | P36: ='Financial Statements'!P37/'Financial Statements'!$P$46 -> 0
A37: Net Property, Plant & Equipment | B37: ='Financial Statements'!B38/'Financial Statements'!$B$46 -> 0.077350368 | C37: ='Financial Statements'!C38/'Financial Statements'!$C$46 -> 0.063229308 | D37: ='Financial Statements'!D38/'Financial Statements'!$D$46 -> 0.052941774 | E37: ='Financial Statements'!E38/'Financial Statements'!$E$46 -> 0.088693177 | F37: ='Financial Statements'!F38/'Financial Statements'!$F$46 -> 0.10562745 | G37: ='Financial Statements'!G38/'Financial Statements'!$G$46 -> 0.13237078 | H37: ='Financial Statements'!H38/'Financial Statements'!$H$46 -> 0.099197666 | I37: ='Financial Statements'!I38/'Financial Statements'!$I$46 -> 0.081630344 | J37: ='Financial Statements'!J38/'Financial Statements'!$J$46 -> 0.11764849 | K37: ='Financial Statements'!K38/'Financial Statements'!$K$46 -> 0.080026777 | L37: ='Financial Statements'!L38/'Financial Statements'!$L$46 -> 0.0016569654 | M37: ='Financial Statements'!M38/'Financial Statements'!$M$46 -> 0.00093297867 | N37: ='Financial Statements'!N38/'Financial Statements'!$N$46 -> 0.00089406462 | O37: ='Financial Statements'!O38/'Financial Statements'!$O$46 -> 0.0007670492 | P37: ='Financial Statements'!P38/'Financial Statements'!$P$46 -> 0.00097495645
A38: Long-Term Investments | B38: ='Financial Statements'!B39/'Financial Statements'!$B$46 -> 0 | C38: ='Financial Statements'!C39/'Financial Statements'!$C$46 -> 0 | D38: ='Financial Statements'!D39/'Financial Statements'!$D$46 -> 0 | E38: ='Financial Statements'!E39/'Financial Statements'!$E$46 -> 0 | F38: ='Financial Statements'!F39/'Financial Statements'!$F$46 -> 0 | G38: ='Financial Statements'!G39/'Financial Statements'!$G$46 -> 0.0044470113 | H38: ='Financial Statements'!H39/'Financial Statements'!$H$46 -> 0.005001563 | I38: ='Financial Statements'!I39/'Financial Statements'!$I$46 -> 0.0060198701 | J38: ='Financial Statements'!J39/'Financial Statements'!$J$46 -> 0.0072604536 | K38: ='Financial Statements'!K39/'Financial Statements'!$K$46 -> 0.023521178 | L38: ='Financial Statements'!L39/'Financial Statements'!$L$46 -> 0.00021236532 | M38: ='Financial Statements'!M39/'Financial Statements'!$M$46 -> 0.00010397861 | N38: ='Financial Statements'!N39/'Financial Statements'!$N$46 -> 8.3034767e-05 | O38: ='Financial Statements'!O39/'Financial Statements'!$O$46 -> 5.6990737e-05 | P38: ='Financial Statements'!P39/'Financial Statements'!$P$46 -> 5.5721514e-05
A39: Goodwill | B39: ='Financial Statements'!B40/'Financial Statements'!$B$46 -> 0.085821414 | C39: ='Financial Statements'!C40/'Financial Statements'!$C$46 -> 0.08385346 | D39: ='Financial Statements'!D40/'Financial Statements'!$D$46 -> 0.062798496 | E39: ='Financial Statements'!E40/'Financial Statements'!$E$46 -> 0.054977315 | F39: ='Financial Statements'!F40/'Financial Statements'!$F$46 -> 0.046494132 | G39: ='Financial Statements'!G40/'Financial Statements'!$G$46 -> 0.035691597 | H39: ='Financial Statements'!H40/'Financial Statements'!$H$46 -> 0.14563579 | I39: ='Financial Statements'!I40/'Financial Statements'!$I$46 -> 0.098422613 | J39: ='Financial Statements'!J40/'Financial Statements'!$J$46 -> 0.10616289 | K39: ='Financial Statements'!K40/'Financial Statements'!$K$46 -> 0.067398978 | L39: ='Financial Statements'!L40/'Financial Statements'!$L$46 -> 0.00060852417 | M39: ='Financial Statements'!M40/'Financial Statements'!$M$46 -> 0.00029794648 | N39: ='Financial Statements'!N40/'Financial Statements'!$N$46 -> 0.00023793274 | O39: ='Financial Statements'!O40/'Financial Statements'!$O$46 -> 0.00016330463 | P39: ='Financial Statements'!P40/'Financial Statements'!$P$46 -> 0.00015966773
A40: Other Intangibles | B40: ='Financial Statements'!B41/'Financial Statements'!$B$46 -> 0.030829052 | C40: ='Financial Statements'!C41/'Financial Statements'!$C$46 -> 0.022523745 | D40: ='Financial Statements'!D41/'Financial Statements'!$D$46 -> 0.010568032 | E40: ='Financial Statements'!E41/'Financial Statements'!$E$46 -> 0.004625923 | F40: ='Financial Statements'!F41/'Financial Statements'!$F$46 -> 0.003385495 | G40: ='Financial Statements'!G41/'Financial Statements'!$G$46 -> 0.0028299163 | H40: ='Financial Statements'!H41/'Financial Statements'!$H$46 -> 0.09506443 | I40: ='Financial Statements'!I41/'Financial Statements'!$I$46 -> 0.052934121 | J40: ='Financial Statements'!J41/'Financial Statements'!$J$46 -> 0.040697392 | K40: ='Financial Statements'!K41/'Financial Statements'!$K$46 -> 0.016918208 | L40: ='Financial Statements'!L41/'Financial Statements'!$L$46 -> 0.00015274918 | M40: ='Financial Statements'!M41/'Financial Statements'!$M$46 -> 7.4789274e-05 | N40: ='Financial Statements'!N41/'Financial Statements'!$N$46 -> 5.9724878e-05 | O40: ='Financial Statements'!O41/'Financial Statements'!$O$46 -> 4.0992043e-05 | P40: ='Financial Statements'!P41/'Financial Statements'!$P$46 -> 4.0079123e-05
A41: Deferred Tax Assets | B41: ='Financial Statements'!B42/'Financial Statements'!$B$46 -> 0 | C41: ='Financial Statements'!C42/'Financial Statements'!$C$46 -> 0 | D41: ='Financial Statements'!D42/'Financial Statements'!$D$46 -> 0 | E41: ='Financial Statements'!E42/'Financial Statements'!$E$46 -> 0.021795214 | F41: ='Financial Statements'!F42/'Financial Statements'!$F$46 -> 0.042130605 | G41: ='Financial Statements'!G42/'Financial Statements'!$G$46 -> 0.031648859 | H41: ='Financial Statements'!H42/'Financial Statements'!$H$46 -> 0.02799486 | I41: ='Financial Statements'!I42/'Financial Statements'!$I$46 -> 0.027655193 | J41: ='Financial Statements'!J42/'Financial Statements'!$J$46 -> 0.082463212 | K41: ='Financial Statements'!K42/'Financial Statements'!$K$46 -> 0.092517648 | L41: ='Financial Statements'!L42/'Financial Statements'!$L$46 -> 0.00083531275 | M41: ='Financial Statements'!M42/'Financial Statements'!$M$46 -> 0.00040898703 | N41: ='Financial Statements'!N42/'Financial Statements'!$N$46 -> 0.000326607 | O41: ='Financial Statements'!O42/'Financial Statements'!$O$46 -> 0.00022416602 | P41: ='Financial Statements'!P42/'Financial Statements'!$P$46 -> 0.00021917369
A42: Other Long-Term Assets | B42: ='Financial Statements'!B43/'Financial Statements'!$B$46 -> 0.012637134 | C42: ='Financial Statements'!C43/'Financial Statements'!$C$46 -> 0.0090909091 | D42: ='Financial Statements'!D43/'Financial Statements'!$D$46 -> 0.0063001727 | E42: ='Financial Statements'!E43/'Financial Statements'!$E$46 -> 0.0065830442 | F42: ='Financial Statements'!F43/'Financial Statements'!$F$46 -> 0.0081251881 | G42: ='Financial Statements'!G43/'Financial Statements'!$G$46 -> 0.0023678891 | H42: ='Financial Statements'!H43/'Financial Statements'!$H$46 -> 0.069466153 | I42: ='Financial Statements'!I43/'Financial Statements'!$I$46 -> 0.080906149 | J42: ='Financial Statements'!J43/'Financial Statements'!$J$46 -> 0.085498519 | K42: ='Financial Statements'!K43/'Financial Statements'!$K$46 -> 0.044942795 | L42: ='Financial Statements'!L43/'Financial Statements'!$L$46 -> 0.00040577436 | M42: ='Financial Statements'!M43/'Financial Statements'!$M$46 -> 0.00019867582 | N42: ='Financial Statements'!N43/'Financial Statements'!$N$46 -> 0.00015865763 | O42: ='Financial Statements'!O43/'Financial Statements'!$O$46 -> 0.00010889433 | P42: ='Financial Statements'!P43/'Financial Statements'!$P$46 -> 0.00010646918
A43: Total Long Term Assets | B43: ='Financial Statements'!B44/'Financial Statements'!$B$46 -> 0.20663797 | C43: ='Financial Statements'!C44/'Financial Statements'!$C$46 -> 0.17869742 | D43: ='Financial Statements'!D44/'Financial Statements'!$D$46 -> 0.13260847 | E43: ='Financial Statements'!E44/'Financial Statements'!$E$46 -> 0.17667467 | F43: ='Financial Statements'!F44/'Financial Statements'!$F$46 -> 0.20576286 | G43: ='Financial Statements'!G44/'Financial Statements'!$G$46 -> 0.20935605 | H43: ='Financial Statements'!H44/'Financial Statements'!$H$46 -> 0.44236046 | I43: ='Financial Statements'!I44/'Financial Statements'!$I$46 -> 0.34756829 | J43: ='Financial Statements'!J44/'Financial Statements'!$J$46 -> 0.43973095 | K43: ='Financial Statements'!K44/'Financial Statements'!$K$46 -> 0.32532558 | L43: ='Financial Statements'!L44/'Financial Statements'!$L$46 -> 0.0038716912 | M43: ='Financial Statements'!M44/'Financial Statements'!$M$46 -> 0.0020173559 | N43: ='Financial Statements'!N44/'Financial Statements'!$N$46 -> 0.0017600216 | O43: ='Financial Statements'!O44/'Financial Statements'!$O$46 -> 0.001361397 | P43: ='Financial Statements'!P44/'Financial Statements'!$P$46 -> 0.0015560677
B44: ='Financial Statements'!B45/'Financial Statements'!$B$46 -> 0 | C44: ='Financial Statements'!C45/'Financial Statements'!$C$46 -> 0 | D44: ='Financial Statements'!D45/'Financial Statements'!$D$46 -> 0 | E44: ='Financial Statements'!E45/'Financial Statements'!$E$46 -> 0 | F44: ='Financial Statements'!F45/'Financial Statements'!$F$46 -> 0 | G44: ='Financial Statements'!G45/'Financial Statements'!$G$46 -> 0 | H44: ='Financial Statements'!H45/'Financial Statements'!$H$46 -> 0 | I44: ='Financial Statements'!I45/'Financial Statements'!$I$46 -> 0 | J44: ='Financial Statements'!J45/'Financial Statements'!$J$46 -> 0 | K44: ='Financial Statements'!K45/'Financial Statements'!$K$46 -> 0 | L44: ='Financial Statements'!L45/'Financial Statements'!$L$46 -> 0 | M44: ='Financial Statements'!M45/'Financial Statements'!$M$46 -> 0 | N44: ='Financial Statements'!N45/'Financial Statements'!$N$46 -> 0 | O44: ='Financial Statements'!O45/'Financial Statements'!$O$46 -> 0 | P44: ='Financial Statements'!P45/'Financial Statements'!$P$46 -> 0
A45: Total Asets | B45: ='Financial Statements'!B46/'Financial Statements'!$B$46 -> 1 | C45: ='Financial Statements'!C46/'Financial Statements'!$C$46 -> 1 | D45: ='Financial Statements'!D46/'Financial Statements'!$D$46 -> 1 | E45: ='Financial Statements'!E46/'Financial Statements'!$E$46 -> 1 | F45: ='Financial Statements'!F46/'Financial Statements'!$F$46 -> 1 | G45: ='Financial Statements'!G46/'Financial Statements'!$G$46 -> 1 | H45: ='Financial Statements'!H46/'Financial Statements'!$H$46 -> 1 | I45: ='Financial Statements'!I46/'Financial Statements'!$I$46 -> 1 | J45: ='Financial Statements'!J46/'Financial Statements'!$J$46 -> 1 | K45: ='Financial Statements'!K46/'Financial Statements'!$K$46 -> 1 | L45: ='Financial Statements'!L46/'Financial Statements'!$L$46 -> 1 | M45: ='Financial Statements'!M46/'Financial Statements'!$M$46 -> 1 | N45: ='Financial Statements'!N46/'Financial Statements'!$N$46 -> 1 | O45: ='Financial Statements'!O46/'Financial Statements'!$O$46 -> 1 | P45: ='Financial Statements'!P46/'Financial Statements'!$P$46 -> 1
A48: Accounts Payable | B48: ='Financial Statements'!B49/'Financial Statements'!$B$72 -> 0.040688793 | C48: ='Financial Statements'!C49/'Financial Statements'!$C$72 -> 0.040162822 | D48: ='Financial Statements'!D49/'Financial Statements'!$D$72 -> 0.049283609 | E48: ='Financial Statements'!E49/'Financial Statements'!$E$72 -> 0.053020194 | F48: ='Financial Statements'!F49/'Financial Statements'!$F$72 -> 0.038444177 | G48: ='Financial Statements'!G49/'Financial Statements'!$G$72 -> 0.039676581 | H48: ='Financial Statements'!H49/'Financial Statements'!$H$72 -> 0.039908305 | I48: ='Financial Statements'!I49/'Financial Statements'!$I$72 -> 0.040351235 | J48: ='Financial Statements'!J49/'Financial Statements'!$J$72 -> 0.028968967 | K48: ='Financial Statements'!K49/'Financial Statements'!$K$72 -> 0.041063169 | L48: ='Financial Statements'!L49/'Financial Statements'!$L$72 -> 0.18410727 | M48: ='Financial Statements'!M49/'Financial Statements'!$M$72 -> 0.12958037 | N48: ='Financial Statements'!N49/'Financial Statements'!$N$72 -> 0.16556752 | O48: ='Financial Statements'!O49/'Financial Statements'!$O$72 -> 0.21306922 | P48: ='Financial Statements'!P49/'Financial Statements'!$P$72 -> 0.13541062
A49: Accrued Expenses | B49: ='Financial Statements'!B50/'Financial Statements'!$B$72 -> 0.018330787 | C49: ='Financial Statements'!C50/'Financial Statements'!$C$72 -> 0.014382632 | D49: ='Financial Statements'!D50/'Financial Statements'!$D$72 -> 0.018087593 | E49: ='Financial Statements'!E50/'Financial Statements'!$E$72 -> 0.019927053 | F49: ='Financial Statements'!F50/'Financial Statements'!$F$72 -> 0.015046645 | G49: ='Financial Statements'!G50/'Financial Statements'!$G$72 -> 0.012879007 | H49: ='Financial Statements'!H50/'Financial Statements'!$H$72 -> 0.010315724 | I49: ='Financial Statements'!I50/'Financial Statements'!$I$72 -> 0.0092561161 | J49: ='Financial Statements'!J50/'Financial Statements'!$J$72 -> 0.0128697 | K49: ='Financial Statements'!K50/'Financial Statements'!$K$72 -> 0.010269596 | L49: ='Financial Statements'!L50/'Financial Statements'!$L$72 -> 0.23013409 | M49: ='Financial Statements'!M50/'Financial Statements'!$M$72 -> 0.17277383 | N49: ='Financial Statements'!N50/'Financial Statements'!$N$72 -> 0.16556752 | O49: ='Financial Statements'!O50/'Financial Statements'!$O$72 -> 0.14204615 | P49: ='Financial Statements'!P50/'Financial Statements'!$P$72 -> 0.18054749
A50: Current Portion of LT Debt | B50: ='Financial Statements'!B51/'Financial Statements'!$B$72 -> 0 | C50: ='Financial Statements'!C51/'Financial Statements'!$C$72 -> 0.1917232 | D50: ='Financial Statements'!D51/'Financial Statements'!$D$72 -> 0.080886089 | E50: ='Financial Statements'!E51/'Financial Statements'!$E$72 -> 0.0013344009 | F50: ='Financial Statements'!F51/'Financial Statements'!$F$72 -> 0 | G50: ='Financial Statements'!G51/'Financial Statements'!$G$72 -> 0 | H50: ='Financial Statements'!H51/'Financial Statements'!$H$72 -> 0.034698343 | I50: ='Financial Statements'!I51/'Financial Statements'!$I$72 -> 0 | J50: ='Financial Statements'!J51/'Financial Statements'!$J$72 -> 0.030353067 | K50: ='Financial Statements'!K51/'Financial Statements'!$K$72 -> 0.01901777 | L50: ='Financial Statements'!L51/'Financial Statements'!$L$72 -> 0.00017170547 | M50: ='Financial Statements'!M51/'Financial Statements'!$M$72 -> 8.4070677e-05 | N50: ='Financial Statements'!N51/'Financial Statements'!$N$72 -> 6.7136778e-05 | O50: ='Financial Statements'!O51/'Financial Statements'!$O$72 -> 4.6079185e-05 | P50: ='Financial Statements'!P51/'Financial Statements'!$P$72 -> 4.5052971e-05
A51: Current Portion of Lease Obligations | B51: ='Financial Statements'!B52/'Financial Statements'!$B$72 -> 0 | C51: ='Financial Statements'!C52/'Financial Statements'!$C$72 -> 0.00054274084 | D51: ='Financial Statements'!D52/'Financial Statements'!$D$72 -> 0.00040646276 | E51: ='Financial Statements'!E52/'Financial Statements'!$E$72 -> 0 | F51: ='Financial Statements'!F52/'Financial Statements'!$F$72 -> 0 | G51: ='Financial Statements'!G52/'Financial Statements'!$G$72 -> 0.0052555588 | H51: ='Financial Statements'!H52/'Financial Statements'!$H$72 -> 0 | I51: ='Financial Statements'!I52/'Financial Statements'!$I$72 -> 0.003258877 | J51: ='Financial Statements'!J52/'Financial Statements'!$J$72 -> 0.0042737118 | K51: ='Financial Statements'!K52/'Financial Statements'!$K$72 -> 0.0034688413 | L51: ='Financial Statements'!L52/'Financial Statements'!$L$72 -> 3.1319077e-05 | M51: ='Financial Statements'!M52/'Financial Statements'!$M$72 -> 1.5334491e-05 | N51: ='Financial Statements'!N52/'Financial Statements'!$N$72 -> 1.2245748e-05 | O51: ='Financial Statements'!O52/'Financial Statements'!$O$72 -> 8.4048434e-06 | P51: ='Financial Statements'!P52/'Financial Statements'!$P$72 -> 8.2176619e-06
A52: Current Income Taxes Payable | B52: ='Financial Statements'!B53/'Financial Statements'!$B$72 -> 0.0004166088 | C52: ='Financial Statements'!C53/'Financial Statements'!$C$72 -> 0.00027137042 | D52: ='Financial Statements'!D53/'Financial Statements'!$D$72 -> 0.00040646276 | E52: ='Financial Statements'!E53/'Financial Statements'!$E$72 -> 0.0029356819 | F52: ='Financial Statements'!F53/'Financial Statements'!$F$72 -> 0.0068462233 | G52: ='Financial Statements'!G53/'Financial Statements'!$G$72 -> 0.003522957 | H52: ='Financial Statements'!H53/'Financial Statements'!$H$72 -> 0 | I52: ='Financial Statements'!I53/'Financial Statements'!$I$72 -> 0.002987304 | J52: ='Financial Statements'!J53/'Financial Statements'!$J$72 -> 0.011339906 | K52: ='Financial Statements'!K53/'Financial Statements'!$K$72 -> 0.004503408 | L52: ='Financial Statements'!L53/'Financial Statements'!$L$72 -> 4.0659854e-05 | M52: ='Financial Statements'!M53/'Financial Statements'!$M$72 -> 1.9907936e-05 | N52: ='Financial Statements'!N53/'Financial Statements'!$N$72 -> 1.5897989e-05 | O52: ='Financial Statements'!O53/'Financial Statements'!$O$72 -> 1.0911551e-05 | P52: ='Financial Statements'!P53/'Financial Statements'!$P$72 -> 1.0668543e-05
A53: Unearned Revenue, Current | B53: ='Financial Statements'!B54/'Financial Statements'!$B$72 -> 0.041105402 | C53: ='Financial Statements'!C54/'Financial Statements'!$C$72 -> 0.043690638 | D53: ='Financial Statements'!D54/'Financial Statements'!$D$72 -> 0.0086373336 | E53: ='Financial Statements'!E54/'Financial Statements'!$E$72 -> 0.004714883 | F53: ='Financial Statements'!F54/'Financial Statements'!$F$72 -> 0.0069214565 | G53: ='Financial Statements'!G54/'Financial Statements'!$G$72 -> 0.0081432284 | H53: ='Financial Statements'!H54/'Financial Statements'!$H$72 -> 0.010003126 | I53: ='Financial Statements'!I54/'Financial Statements'!$I$72 -> 0.0067893272 | J53: ='Financial Statements'!J54/'Financial Statements'!$J$72 -> 0.0085959885 | K53: ='Financial Statements'!K54/'Financial Statements'!$K$72 -> 0.011623661 | L53: ='Financial Statements'!L54/'Financial Statements'!$L$72 -> 0.46026818 | M53: ='Financial Statements'!M54/'Financial Statements'!$M$72 -> 0.51832148 | N53: ='Financial Statements'!N54/'Financial Statements'!$N$72 -> 0.49670257 | O53: ='Financial Statements'!O54/'Financial Statements'!$O$72 -> 0.42613845 | P53: ='Financial Statements'!P54/'Financial Statements'!$P$72 -> 0.54164247
A54: Other Current Liabilities | B54: ='Financial Statements'!B55/'Financial Statements'!$B$72 -> 0.023885571 | C54: ='Financial Statements'!C55/'Financial Statements'!$C$72 -> 0.028222524 | D54: ='Financial Statements'!D55/'Financial Statements'!$D$72 -> 0.023981303 | E54: ='Financial Statements'!E55/'Financial Statements'!$E$72 -> 0.020638733 | F54: ='Financial Statements'!F55/'Financial Statements'!$F$72 -> 0.032726452 | G54: ='Financial Statements'!G55/'Financial Statements'!$G$72 -> 0.033554721 | H54: ='Financial Statements'!H55/'Financial Statements'!$H$72 -> 0.041401827 | I54: ='Financial Statements'!I55/'Financial Statements'!$I$72 -> 0.035462919 | J54: ='Financial Statements'!J55/'Financial Statements'!$J$72 -> 0.062964402 | K54: ='Financial Statements'!K55/'Financial Statements'!$K$72 -> 0.071795886 | L54: ='Financial Statements'!L55/'Financial Statements'!$L$72 -> 0.11506704 | M54: ='Financial Statements'!M55/'Financial Statements'!$M$72 -> 0.17277383 | N54: ='Financial Statements'!N55/'Financial Statements'!$N$72 -> 0.16556752 | O54: ='Financial Statements'!O55/'Financial Statements'!$O$72 -> 0.21306922 | P54: ='Financial Statements'!P55/'Financial Statements'!$P$72 -> 0.13541062
A55: Total Current Liabilities | B55: ='Financial Statements'!B56/'Financial Statements'!$B$72 -> 0.12442716 | C55: ='Financial Statements'!C56/'Financial Statements'!$C$72 -> 0.31899593 | D55: ='Financial Statements'!D56/'Financial Statements'!$D$72 -> 0.18168885 | E55: ='Financial Statements'!E56/'Financial Statements'!$E$72 -> 0.10257095 | F55: ='Financial Statements'!F56/'Financial Statements'!$F$72 -> 0.099984953 | G55: ='Financial Statements'!G56/'Financial Statements'!$G$72 -> 0.10303205 | H55: ='Financial Statements'!H56/'Financial Statements'!$H$72 -> 0.13632732 | I55: ='Financial Statements'!I56/'Financial Statements'!$I$72 -> 0.098105778 | J55: ='Financial Statements'!J56/'Financial Statements'!$J$72 -> 0.15936574 | K55: ='Financial Statements'!K56/'Financial Statements'!$K$72 -> 0.16174233 | L55: ='Financial Statements'!L56/'Financial Statements'!$L$72 -> 0.98982026 | M55: ='Financial Statements'!M56/'Financial Statements'!$M$72 -> 0.99356882 | N55: ='Financial Statements'!N56/'Financial Statements'!$N$72 -> 0.99350042 | O55: ='Financial Statements'!O56/'Financial Statements'!$O$72 -> 0.99438843 | P55: ='Financial Statements'!P56/'Financial Statements'!$P$72 -> 0.99307513
B56: ='Financial Statements'!B57/'Financial Statements'!$B$72 -> 0 | C56: ='Financial Statements'!C57/'Financial Statements'!$C$72 -> 0 | D56: ='Financial Statements'!D57/'Financial Statements'!$D$72 -> 0 | E56: ='Financial Statements'!E57/'Financial Statements'!$E$72 -> 0 | F56: ='Financial Statements'!F57/'Financial Statements'!$F$72 -> 0 | G56: ='Financial Statements'!G57/'Financial Statements'!$G$72 -> 0 | H56: ='Financial Statements'!H57/'Financial Statements'!$H$72 -> 0 | I56: ='Financial Statements'!I57/'Financial Statements'!$I$72 -> 0 | J56: ='Financial Statements'!J57/'Financial Statements'!$J$72 -> 0 | K56: ='Financial Statements'!K57/'Financial Statements'!$K$72 -> 0 | L56: ='Financial Statements'!L57/'Financial Statements'!$L$72 -> 0 | M56: ='Financial Statements'!M57/'Financial Statements'!$M$72 -> 0 | N56: ='Financial Statements'!N57/'Financial Statements'!$N$72 -> 0 | O56: ='Financial Statements'!O57/'Financial Statements'!$O$72 -> 0 | P56: ='Financial Statements'!P57/'Financial Statements'!$P$72 -> 0
A57: Additional Funding Needed | B57: ='Financial Statements'!B58/'Financial Statements'!$B$72 -> 0 | C57: ='Financial Statements'!C58/'Financial Statements'!$C$72 -> 0 | D57: ='Financial Statements'!D58/'Financial Statements'!$D$72 -> 0 | E57: ='Financial Statements'!E58/'Financial Statements'!$E$72 -> 0 | F57: ='Financial Statements'!F58/'Financial Statements'!$F$72 -> 0 | G57: ='Financial Statements'!G58/'Financial Statements'!$G$72 -> 0 | H57: ='Financial Statements'!H58/'Financial Statements'!$H$72 -> 0 | I57: ='Financial Statements'!I58/'Financial Statements'!$I$72 -> 0 | J57: ='Financial Statements'!J58/'Financial Statements'!$J$72 -> 0 | K57: ='Financial Statements'!K58/'Financial Statements'!$K$72 -> 0 | L57: ='Financial Statements'!L58/'Financial Statements'!$L$72 -> 0 | M57: ='Financial Statements'!M58/'Financial Statements'!$M$72 -> 0 | N57: ='Financial Statements'!N58/'Financial Statements'!$N$72 -> 0 | O57: ='Financial Statements'!O58/'Financial Statements'!$O$72 -> 0 | P57: ='Financial Statements'!P58/'Financial Statements'!$P$72 -> 0
B58: ='Financial Statements'!B59/'Financial Statements'!$B$72 -> 0 | C58: ='Financial Statements'!C59/'Financial Statements'!$C$72 -> 0 | D58: ='Financial Statements'!D59/'Financial Statements'!$D$72 -> 0 | E58: ='Financial Statements'!E59/'Financial Statements'!$E$72 -> 0 | F58: ='Financial Statements'!F59/'Financial Statements'!$F$72 -> 0 | G58: ='Financial Statements'!G59/'Financial Statements'!$G$72 -> 0 | H58: ='Financial Statements'!H59/'Financial Statements'!$H$72 -> 0 | I58: ='Financial Statements'!I59/'Financial Statements'!$I$72 -> 0 | J58: ='Financial Statements'!J59/'Financial Statements'!$J$72 -> 0 | K58: ='Financial Statements'!K59/'Financial Statements'!$K$72 -> 0 | L58: ='Financial Statements'!L59/'Financial Statements'!$L$72 -> 0 | M58: ='Financial Statements'!M59/'Financial Statements'!$M$72 -> 0 | N58: ='Financial Statements'!N59/'Financial Statements'!$N$72 -> 0 | O58: ='Financial Statements'!O59/'Financial Statements'!$O$72 -> 0 | P58: ='Financial Statements'!P59/'Financial Statements'!$P$72 -> 0
A59: Long-Term Debt | B59: ='Financial Statements'!B60/'Financial Statements'!$B$72 -> 0.19219553 | C59: ='Financial Statements'!C60/'Financial Statements'!$C$72 -> 0.00094979647 | D59: ='Financial Statements'!D60/'Financial Statements'!$D$72 -> 0.20150391 | E59: ='Financial Statements'!E60/'Financial Statements'!$E$72 -> 0.17658571 | F59: ='Financial Statements'!F60/'Financial Statements'!$F$72 -> 0.14956365 | G59: ='Financial Statements'!G60/'Financial Statements'!$G$72 -> 0.11498701 | H59: ='Financial Statements'!H60/'Financial Statements'!$H$72 -> 0.20714807 | I59: ='Financial Statements'!I60/'Financial Statements'!$I$72 -> 0.24771992 | J59: ='Financial Statements'!J60/'Financial Statements'!$J$72 -> 0.23561265 | K59: ='Financial Statements'!K60/'Financial Statements'!$K$72 -> 0.12869705 | L59: ='Financial Statements'!L60/'Financial Statements'!$L$72 -> 0.0011619652 | M59: ='Financial Statements'!M60/'Financial Statements'!$M$72 -> 0.00056892308 | N59: ='Financial Statements'!N60/'Financial Statements'!$N$72 -> 0.000454328 | O59: ='Financial Statements'!O60/'Financial Statements'!$O$72 -> 0.00031182706 | P59: ='Financial Statements'!P60/'Financial Statements'!$P$72 -> 0.00030488246
A60: Unearned Revenue Non-Current | B60: ='Financial Statements'!B61/'Financial Statements'!$B$72 -> 0.014997917 | C60: ='Financial Statements'!C61/'Financial Statements'!$C$72 -> 0.0059701493 | D60: ='Financial Statements'!D61/'Financial Statements'!$D$72 -> 0.00040646276 | E60: ='Financial Statements'!E61/'Financial Statements'!$E$72 -> 0.0013344009 | F60: ='Financial Statements'!F61/'Financial Statements'!$F$72 -> 0.0034607283 | G60: ='Financial Statements'!G61/'Financial Statements'!$G$72 -> 0.0034652036 | H60: ='Financial Statements'!H61/'Financial Statements'!$H$72 -> 0.0056614914 | I60: ='Financial Statements'!I61/'Financial Statements'!$I$72 -> 0.0045714803 | J60: ='Financial Statements'!J61/'Financial Statements'!$J$72 -> 0.0052935749 | K60: ='Financial Statements'!K61/'Financial Statements'!$K$72 -> 0.0087177459 | L60: ='Financial Statements'!L61/'Financial Statements'!$L$72 -> 7.8709786e-05 | M60: ='Financial Statements'!M61/'Financial Statements'!$M$72 -> 3.8537998e-05 | N60: ='Financial Statements'!N61/'Financial Statements'!$N$72 -> 3.0775499e-05 | O60: ='Financial Statements'!O61/'Financial Statements'!$O$72 -> 2.1122699e-05 | P60: ='Financial Statements'!P61/'Financial Statements'!$P$72 -> 2.0652282e-05
A61: Pension & Other Post-Retire. Benefits | B61: ='Financial Statements'!B62/'Financial Statements'!$B$72 -> 0 | C61: ='Financial Statements'!C62/'Financial Statements'!$C$72 -> 0 | D61: ='Financial Statements'!D62/'Financial Statements'!$D$72 -> 0.0010161569 | E61: ='Financial Statements'!E62/'Financial Statements'!$E$72 -> 0.0010675207 | F61: ='Financial Statements'!F62/'Financial Statements'!$F$72 -> 0.0015046645 | G61: ='Financial Statements'!G62/'Financial Statements'!$G$72 -> 0.0012705746 | H61: ='Financial Statements'!H62/'Financial Statements'!$H$72 -> 0 | I61: ='Financial Statements'!I62/'Financial Statements'!$I$72 -> 0 | J61: ='Financial Statements'!J62/'Financial Statements'!$J$72 -> 0 | K61: ='Financial Statements'!K62/'Financial Statements'!$K$72 -> 0 | L61: ='Financial Statements'!L62/'Financial Statements'!$L$72 -> 0 | M61: ='Financial Statements'!M62/'Financial Statements'!$M$72 -> 0 | N61: ='Financial Statements'!N62/'Financial Statements'!$N$72 -> 0 | O61: ='Financial Statements'!O62/'Financial Statements'!$O$72 -> 0 | P61: ='Financial Statements'!P62/'Financial Statements'!$P$72 -> 0
A62: Def. Tax Liability, Non-Curr. | B62: ='Financial Statements'!B63/'Financial Statements'!$B$72 -> 0.032217748 | C62: ='Financial Statements'!C63/'Financial Statements'!$C$72 -> 0.040841248 | D62: ='Financial Statements'!D63/'Financial Statements'!$D$72 -> 0.014327812 | E62: ='Financial Statements'!E63/'Financial Statements'!$E$72 -> 0.001601281 | F62: ='Financial Statements'!F63/'Financial Statements'!$F$72 -> 0.0014294312 | G62: ='Financial Statements'!G63/'Financial Statements'!$G$72 -> 0.0016748484 | H62: ='Financial Statements'!H63/'Financial Statements'!$H$72 -> 0.0083706714 | I62: ='Financial Statements'!I63/'Financial Statements'!$I$72 -> 0.0055446172 | J62: ='Financial Statements'!J63/'Financial Statements'!$J$72 -> 0.005997766 | K62: ='Financial Statements'!K63/'Financial Statements'!$K$72 -> 0.0070289679 | L62: ='Financial Statements'!L63/'Financial Statements'!$L$72 -> 6.346234e-05 | M62: ='Financial Statements'!M63/'Financial Statements'!$M$72 -> 3.1072522e-05 | N62: ='Financial Statements'!N63/'Financial Statements'!$N$72 -> 2.4813753e-05 | O62: ='Financial Statements'!O63/'Financial Statements'!$O$72 -> 1.7030867e-05 | P62: ='Financial Statements'!P63/'Financial Statements'!$P$72 -> 1.6651578e-05
A63: Capital Leases | B63: ='Financial Statements'!B64/'Financial Statements'!$B$72 -> 0.0019441744 | C63: ='Financial Statements'!C64/'Financial Statements'!$C$72 -> 0.0013568521 | D63: ='Financial Statements'!D64/'Financial Statements'!$D$72 -> 0 | E63: ='Financial Statements'!E64/'Financial Statements'!$E$72 -> 0 | F63: ='Financial Statements'!F64/'Financial Statements'!$F$72 -> 0 | G63: ='Financial Statements'!G64/'Financial Statements'!$G$72 -> 0.032399653 | H63: ='Financial Statements'!H64/'Financial Statements'!$H$72 -> 0.02202077 | I63: ='Financial Statements'!I64/'Financial Statements'!$I$72 -> 0.016769638 | J63: ='Financial Statements'!J64/'Financial Statements'!$J$72 -> 0.021902773 | K63: ='Financial Statements'!K64/'Financial Statements'!$K$72 -> 0.017024708 | L63: ='Financial Statements'!L64/'Financial Statements'!$L$72 -> 0.00015371073 | M63: ='Financial Statements'!M64/'Financial Statements'!$M$72 -> 7.526007e-05 | N63: ='Financial Statements'!N64/'Financial Statements'!$N$72 -> 6.0100844e-05 | O63: ='Financial Statements'!O64/'Financial Statements'!$O$72 -> 4.1250087e-05 | P63: ='Financial Statements'!P64/'Financial Statements'!$P$72 -> 4.0331419e-05
A64: Other Non-Current Liabilities | B64: ='Financial Statements'!B65/'Financial Statements'!$B$72 -> 0.020691571 | C64: ='Financial Statements'!C65/'Financial Statements'!$C$72 -> 0.02550882 | D64: ='Financial Statements'!D65/'Financial Statements'!$D$72 -> 0.0155472 | E64: ='Financial Statements'!E65/'Financial Statements'!$E$72 -> 0.052219553 | F64: ='Financial Statements'!F65/'Financial Statements'!$F$72 -> 0.041227806 | G64: ='Financial Statements'!G65/'Financial Statements'!$G$72 -> 0.038348253 | H64: ='Financial Statements'!H65/'Financial Statements'!$H$72 -> 0.033725817 | I64: ='Financial Statements'!I65/'Financial Statements'!$I$72 -> 0.025029986 | J64: ='Financial Statements'!J65/'Financial Statements'!$J$72 -> 0.035160993 | K64: ='Financial Statements'!K65/'Financial Statements'!$K$72 -> 0.02291261 | L64: ='Financial Statements'!L65/'Financial Statements'!$L$72 -> 0.00020687075 | M64: ='Financial Statements'!M65/'Financial Statements'!$M$72 -> 0.00010128835 | N64: ='Financial Statements'!N65/'Financial Statements'!$N$72 -> 8.088639e-05 | O64: ='Financial Statements'!O65/'Financial Statements'!$O$72 -> 5.5516203e-05 | P64: ='Financial Statements'!P65/'Financial Statements'!$P$72 -> 5.4279819e-05
A65: Total Long-Term Liabilities | B65: ='Financial Statements'!B66/'Financial Statements'!$B$72 -> 0.26204694 | C65: ='Financial Statements'!C66/'Financial Statements'!$C$72 -> 0.074626866 | D65: ='Financial Statements'!D66/'Financial Statements'!$D$72 -> 0.23280154 | E65: ='Financial Statements'!E66/'Financial Statements'!$E$72 -> 0.23280847 | F65: ='Financial Statements'!F66/'Financial Statements'!$F$72 -> 0.19718628 | G65: ='Financial Statements'!G66/'Financial Statements'!$G$72 -> 0.19214554 | H65: ='Financial Statements'!H66/'Financial Statements'!$H$72 -> 0.27692682 | I65: ='Financial Statements'!I66/'Financial Statements'!$I$72 -> 0.29963564 | J65: ='Financial Statements'!J66/'Financial Statements'!$J$72 -> 0.30396775 | K65: ='Financial Statements'!K66/'Financial Statements'!$K$72 -> 0.18438109 | L65: ='Financial Statements'!L66/'Financial Statements'!$L$72 -> 0.0016647188 | M65: ='Financial Statements'!M66/'Financial Statements'!$M$72 -> 0.00081508202 | N65: ='Financial Statements'!N66/'Financial Statements'!$N$72 -> 0.00065090449 | O65: ='Financial Statements'!O66/'Financial Statements'!$O$72 -> 0.00044674692 | P65: ='Financial Statements'!P66/'Financial Statements'!$P$72 -> 0.00043679756
B66: ='Financial Statements'!B67/'Financial Statements'!$B$72 -> 0 | C66: ='Financial Statements'!C67/'Financial Statements'!$C$72 -> 0 | D66: ='Financial Statements'!D67/'Financial Statements'!$D$72 -> 0 | E66: ='Financial Statements'!E67/'Financial Statements'!$E$72 -> 0 | F66: ='Financial Statements'!F67/'Financial Statements'!$F$72 -> 0 | G66: ='Financial Statements'!G67/'Financial Statements'!$G$72 -> 0 | H66: ='Financial Statements'!H67/'Financial Statements'!$H$72 -> 0 | I66: ='Financial Statements'!I67/'Financial Statements'!$I$72 -> 0 | J66: ='Financial Statements'!J67/'Financial Statements'!$J$72 -> 0 | K66: ='Financial Statements'!K67/'Financial Statements'!$K$72 -> 0 | L66: ='Financial Statements'!L67/'Financial Statements'!$L$72 -> 0 | M66: ='Financial Statements'!M67/'Financial Statements'!$M$72 -> 0 | N66: ='Financial Statements'!N67/'Financial Statements'!$N$72 -> 0 | O66: ='Financial Statements'!O67/'Financial Statements'!$O$72 -> 0 | P66: ='Financial Statements'!P67/'Financial Statements'!$P$72 -> 0
A67: Total Liabilities | B67: ='Financial Statements'!B68/'Financial Statements'!$B$72 -> 0.3864741 | C67: ='Financial Statements'!C68/'Financial Statements'!$C$72 -> 0.3936228 | D67: ='Financial Statements'!D68/'Financial Statements'!$D$72 -> 0.4144904 | E67: ='Financial Statements'!E68/'Financial Statements'!$E$72 -> 0.33537941 | F67: ='Financial Statements'!F68/'Financial Statements'!$F$72 -> 0.29717123 | G67: ='Financial Statements'!G68/'Financial Statements'!$G$72 -> 0.29517759 | H67: ='Financial Statements'!H68/'Financial Statements'!$H$72 -> 0.41325414 | I67: ='Financial Statements'!I68/'Financial Statements'!$I$72 -> 0.39774142 | J67: ='Financial Statements'!J68/'Financial Statements'!$J$72 -> 0.4633335 | K67: ='Financial Statements'!K68/'Financial Statements'!$K$72 -> 0.34612342 | L67: ='Financial Statements'!L68/'Financial Statements'!$L$72 -> 0.99148498 | M67: ='Financial Statements'!M68/'Financial Statements'!$M$72 -> 0.9943839 | N67: ='Financial Statements'!N68/'Financial Statements'!$N$72 -> 0.99415132 | O67: ='Financial Statements'!O68/'Financial Statements'!$O$72 -> 0.99483518 | P67: ='Financial Statements'!P68/'Financial Statements'!$P$72 -> 0.99351193
B68: ='Financial Statements'!B69/'Financial Statements'!$B$72 -> 0 | C68: ='Financial Statements'!C69/'Financial Statements'!$C$72 -> 0 | D68: ='Financial Statements'!D69/'Financial Statements'!$D$72 -> 0 | E68: ='Financial Statements'!E69/'Financial Statements'!$E$72 -> 0 | F68: ='Financial Statements'!F69/'Financial Statements'!$F$72 -> 0 | G68: ='Financial Statements'!G69/'Financial Statements'!$G$72 -> 0 | H68: ='Financial Statements'!H69/'Financial Statements'!$H$72 -> 0 | I68: ='Financial Statements'!I69/'Financial Statements'!$I$72 -> 0 | J68: ='Financial Statements'!J69/'Financial Statements'!$J$72 -> 0 | K68: ='Financial Statements'!K69/'Financial Statements'!$K$72 -> 0 | L68: ='Financial Statements'!L69/'Financial Statements'!$L$72 -> 0 | M68: ='Financial Statements'!M69/'Financial Statements'!$M$72 -> 0 | N68: ='Financial Statements'!N69/'Financial Statements'!$N$72 -> 0 | O68: ='Financial Statements'!O69/'Financial Statements'!$O$72 -> 0 | P68: ='Financial Statements'!P69/'Financial Statements'!$P$72 -> 0
A69: Total Stockholders' Equity | B69: ='Financial Statements'!B70/'Financial Statements'!$B$72 -> 0.6135259 | C69: ='Financial Statements'!C70/'Financial Statements'!$C$72 -> 0.6063772 | D69: ='Financial Statements'!D70/'Financial Statements'!$D$72 -> 0.5855096 | E69: ='Financial Statements'!E70/'Financial Statements'!$E$72 -> 0.66462059 | F69: ='Financial Statements'!F70/'Financial Statements'!$F$72 -> 0.70282877 | G69: ='Financial Statements'!G70/'Financial Statements'!$G$72 -> 0.70482241 | H69: ='Financial Statements'!H70/'Financial Statements'!$H$72 -> 0.58674586 | I69: ='Financial Statements'!I70/'Financial Statements'!$I$72 -> 0.60225858 | J69: ='Financial Statements'!J70/'Financial Statements'!$J$72 -> 0.5366665 | K69: ='Financial Statements'!K70/'Financial Statements'!$K$72 -> 0.65387658 | L69: ='Financial Statements'!L70/'Financial Statements'!$L$72 -> 0.0085150164 | M69: ='Financial Statements'!M70/'Financial Statements'!$M$72 -> 0.0056161004 | N69: ='Financial Statements'!N70/'Financial Statements'!$N$72 -> 0.0058486792 | O69: ='Financial Statements'!O70/'Financial Statements'!$O$72 -> 0.0051648187 | P69: ='Financial Statements'!P70/'Financial Statements'!$P$72 -> 0.0064880686
B70: ='Financial Statements'!B71/'Financial Statements'!$B$72 -> 0 | C70: ='Financial Statements'!C71/'Financial Statements'!$C$72 -> 0 | D70: ='Financial Statements'!D71/'Financial Statements'!$D$72 -> 0 | E70: ='Financial Statements'!E71/'Financial Statements'!$E$72 -> 0 | F70: ='Financial Statements'!F71/'Financial Statements'!$F$72 -> 0 | G70: ='Financial Statements'!G71/'Financial Statements'!$G$72 -> 0 | H70: ='Financial Statements'!H71/'Financial Statements'!$H$72 -> 0 | I70: ='Financial Statements'!I71/'Financial Statements'!$I$72 -> 0 | J70: ='Financial Statements'!J71/'Financial Statements'!$J$72 -> 0 | K70: ='Financial Statements'!K71/'Financial Statements'!$K$72 -> 0 | L70: ='Financial Statements'!L71/'Financial Statements'!$L$72 -> 0 | M70: ='Financial Statements'!M71/'Financial Statements'!$M$72 -> 0 | N70: ='Financial Statements'!N71/'Financial Statements'!$N$72 -> 0 | O70: ='Financial Statements'!O71/'Financial Statements'!$O$72 -> 0 | P70: ='Financial Statements'!P71/'Financial Statements'!$P$72 -> 0
A71: Total Liabilities And Equity | B71: ='Financial Statements'!B72/'Financial Statements'!$B$72 -> 1 | C71: ='Financial Statements'!C72/'Financial Statements'!$C$72 -> 1 | D71: ='Financial Statements'!D72/'Financial Statements'!$D$72 -> 1 | E71: ='Financial Statements'!E72/'Financial Statements'!$E$72 -> 1 | F71: ='Financial Statements'!F72/'Financial Statements'!$F$72 -> 1 | G71: ='Financial Statements'!G72/'Financial Statements'!$G$72 -> 1 | H71: ='Financial Statements'!H72/'Financial Statements'!$H$72 -> 1 | I71: ='Financial Statements'!I72/'Financial Statements'!$I$72 -> 1 | J71: ='Financial Statements'!J72/'Financial Statements'!$J$72 -> 1 | K71: ='Financial Statements'!K72/'Financial Statements'!$K$72 -> 1 | L71: ='Financial Statements'!L72/'Financial Statements'!$L$72 -> 1 | M71: ='Financial Statements'!M72/'Financial Statements'!$M$72 -> 1 | N71: ='Financial Statements'!N72/'Financial Statements'!$N$72 -> 1 | O71: ='Financial Statements'!O72/'Financial Statements'!$O$72 -> 1 | P71: ='Financial Statements'!P72/'Financial Statements'!$P$72 -> 1

Sheet Forecast Assumptions
I1: Historic | M1: Forecast
B2: 42369 | C2: 42735 | D2: 43100 | E2: 43465 | F2: 43830 | G2: 44196 | H2: 44561 | I2: 44926 | J2: 45291 | K2: 45292 | L2: 45658 | M2: 46023 | N2: 46388 | O2: 46753 | P2: 47119
A3: Revenue Growth Rate | C3: =('Financial Statements'!C6-'Financial Statements'!B6)/'Financial Statements'!B6 -> 0.070055532 | D3: =('Financial Statements'!D6-'Financial Statements'!C6)/'Financial Statements'!C6 -> 0.37924152 | E3: =('Financial Statements'!E6-'Financial Statements'!D6)/'Financial Statements'!D6 -> 0.40578871 | F3: =('Financial Statements'!F6-'Financial Statements'!E6)/'Financial Statements'!E6 -> 0.2060943 | G3: =('Financial Statements'!G6-'Financial Statements'!F6)/'Financial Statements'!F6 -> -0.068111984 | H3: =('Financial Statements'!H6-'Financial Statements'!G6)/'Financial Statements'!G6 -> 0.52729438 | I3: =('Financial Statements'!I6-'Financial Statements'!H6)/'Financial Statements'!H6 -> 0.61403298 | J3: =('Financial Statements'!J6-'Financial Statements'!I6)/'Financial Statements'!I6 -> 0.002229323 | K3: =('Financial Statements'!K6-'Financial Statements'!J6)/'Financial Statements'!J6 -> 1.2585453 | L3: 0.1 | M3: 0.15 | N3: 0.2 | O3: 0.25 | P3: 0.3
A4: COGS/Sales | C4: ='Financial Statements'!C7/'Financial Statements'!C6 -> 0.43892216 | D4: ='Financial Statements'!D7/'Financial Statements'!D6 -> 0.41201158 | E4: ='Financial Statements'!E7/'Financial Statements'!E6 -> 0.40065884 | F4: ='Financial Statements'!F7/'Financial Statements'!F6 -> 0.38793103 | G4: ='Financial Statements'!G7/'Financial Statements'!G6 -> 0.38010625 | H4: ='Financial Statements'!H7/'Financial Statements'!H6 -> 0.36689655 | I4: ='Financial Statements'!I7/'Financial Statements'!I6 -> 0.35070967 | J4: ='Financial Statements'!J7/'Financial Statements'!J6 -> 0.43071106 | K4: ='Financial Statements'!K7/'Financial Statements'!K6 -> 0.27282427 | L4: 0.35 | M4: 0.35 | N4: 0.35 | O4: 0.35 | P4: 0.35
A5: SG&A/Sales | C5: ='Financial Statements'!C10/'Financial Statements'!C6 -> 0.12015968 | D5: ='Financial Statements'!D10/'Financial Statements'!D6 -> 0.095947902 | E5: ='Financial Statements'!E10/'Financial Statements'!E6 -> 0.083899526 | F5: ='Financial Statements'!F10/'Financial Statements'!F6 -> 0.084585183 | G5: ='Financial Statements'!G10/'Financial Statements'!G6 -> 0.10010991 | H5: ='Financial Statements'!H10/'Financial Statements'!H6 -> 0.11466267 | I5: ='Financial Statements'!I10/'Financial Statements'!I6 -> 0.080478561 | J5: ='Financial Statements'!J10/'Financial Statements'!J6 -> 0.090457478 | K5: ='Financial Statements'!K10/'Financial Statements'!K6 -> 0.043563901 | L5: 0.1 | M5: 0.1 | N5: 0.1 | O5: 0.1 | P5: 0.1
A6: R&D/Sales | C6: ='Financial Statements'!C11/'Financial Statements'!C6 -> 0.26566866 | D6: ='Financial Statements'!D11/'Financial Statements'!D6 -> 0.21172214 | E6: ='Financial Statements'!E11/'Financial Statements'!E6 -> 0.18499074 | F6: ='Financial Statements'!F11/'Financial Statements'!F6 -> 0.20279959 | G6: ='Financial Statements'!G11/'Financial Statements'!G6 -> 0.25911339 | H6: ='Financial Statements'!H11/'Financial Statements'!H6 -> 0.23532234 | I6: ='Financial Statements'!I11/'Financial Statements'!I6 -> 0.19573456 | J6: ='Financial Statements'!J11/'Financial Statements'!J6 -> 0.27207681 | K6: ='Financial Statements'!K11/'Financial Statements'!K6 -> 0.14239519 | L6: 0.2 | M6: 0.2 | N6: 0.2 | O6: 0.2 | P6: 0.2
A7: Interest Rate Earned on Surplus Cash | L7: 0.04 | M7: 0.04 | N7: 0.04 | O7: 0.04 | P7: 0.04
A8: Interest Rate Paid on Additional financing | L8: 0.06 | M8: 0.06 | N8: 0.06 | O8: 0.06 | P8: 0.06
A9: Tax Rate | C9: 0.16 | D9: 0.3 | E9: 0.14 | F9: 0.05 | G9: -0.06 | H9: 0.06 | I9: 0.15 | J9: 0.13 | K9: 0.22 | L9: 0.21 | M9: 0.22 | N9: 0.23 | O9: 0.24 | P9: 0.25
A10: Average Shares Outstanding | K10: 2469
A12: AR/Sales | C12: ='Financial Statements'!C30/'Financial Statements'!C6 -> 0.1007984 | D12: ='Financial Statements'!D30/'Financial Statements'!D6 -> 0.1195369 | E12: ='Financial Statements'!E30/'Financial Statements'!E6 -> 0.13022442 | F12: ='Financial Statements'!F30/'Financial Statements'!F6 -> 0.12154319 | G12: ='Financial Statements'!G30/'Financial Statements'!G6 -> 0.15176772 | H12: ='Financial Statements'!H30/'Financial Statements'!H6 -> 0.14566717 | I12: ='Financial Statements'!I30/'Financial Statements'!I6 -> 0.17277253 | J12: ='Financial Statements'!J30/'Financial Statements'!J6 -> 0.14187736 | K12: ='Financial Statements'!K30/'Financial Statements'!K6 -> 0.1641279 | L12: 0.16 | M12: 0.16 | N12: 0.16 | O12: 0.16 | P12: 0.16
A13: Inventory/Sales | C13: ='Financial Statements'!C31/'Financial Statements'!C6 -> 0.083433134 | D13: ='Financial Statements'!D31/'Financial Statements'!D6 -> 0.11490593 | E13: ='Financial Statements'!E31/'Financial Statements'!E6 -> 0.081943587 | F13: ='Financial Statements'!F31/'Financial Statements'!F6 -> 0.13443155 | G13: ='Financial Statements'!G31/'Financial Statements'!G6 -> 0.089668437 | H13: ='Financial Statements'!H31/'Financial Statements'!H6 -> 0.10950525 | I13: ='Financial Statements'!I31/'Financial Statements'!I6 -> 0.096789775 | J13: ='Financial Statements'!J31/'Financial Statements'!J6 -> 0.19125825 | K13: ='Financial Statements'!K31/'Financial Statements'!K6 -> 0.086701028 | L13: 0.09 | M13: 0.09 | N13: 0.09 | O13: 0.09 | P13: 0.09
A14: Prepaid Expenses/Sales | C14: ='Financial Statements'!C32/'Financial Statements'!C6 -> 0.018562874 | D14: ='Financial Statements'!D32/'Financial Statements'!D6 -> 0.0170767 | E14: ='Financial Statements'!E32/'Financial Statements'!E6 -> 0.0088532016 | F14: ='Financial Statements'!F32/'Financial Statements'!F6 -> 0.011608057 | G14: ='Financial Statements'!G32/'Financial Statements'!G6 -> 0.014379923 | H14: ='Financial Statements'!H32/'Financial Statements'!H6 -> 0.014332834 | I14: ='Financial Statements'!I32/'Financial Statements'!I6 -> 0.01359887 | J14: ='Financial Statements'!J32/'Financial Statements'!J6 -> 0.029324535 | K14: ='Financial Statements'!K32/'Financial Statements'!K6 -> 0.050556449 | L14: 0.05 | M14: 0.05 | N14: 0.05 | O14: 0.05 | P14: 0.05
A15: Net PPE/Sales | C15: ='Financial Statements'!C38/'Financial Statements'!C6 -> 0.093013972 | D15: ='Financial Statements'!D38/'Financial Statements'!D6 -> 0.075397974 | E15: ='Financial Statements'!E38/'Financial Statements'!E6 -> 0.10263537 | F15: ='Financial Statements'!F38/'Financial Statements'!F6 -> 0.11983612 | G15: ='Financial Statements'!G38/'Financial Statements'!G6 -> 0.20992856 | H15: ='Financial Statements'!H38/'Financial Statements'!H6 -> 0.17127436 | I15: ='Financial Statements'!I38/'Financial Statements'!I6 -> 0.13401947 | J15: ='Financial Statements'!J38/'Financial Statements'!J6 -> 0.17961741 | K15: ='Financial Statements'!K38/'Financial Statements'!K6 -> 0.08633991 | L15: 0.18 | M15: 0.18 | N15: 0.18 | O15: 0.18 | P15: 0.18
A17: Payables/Sales | C17: ='Financial Statements'!C49/'Financial Statements'!C6 -> 0.059081836 | D17: ='Financial Statements'!D49/'Financial Statements'!D6 -> 0.070188133 | E17: ='Financial Statements'!E49/'Financial Statements'!E6 -> 0.061354746 | F17: ='Financial Statements'!F49/'Financial Statements'!F6 -> 0.043615568 | G17: ='Financial Statements'!G49/'Financial Statements'!G6 -> 0.062923612 | H17: ='Financial Statements'!H49/'Financial Statements'!H6 -> 0.068905547 | I17: ='Financial Statements'!I49/'Financial Statements'!I6 -> 0.066248049 | J17: ='Financial Statements'!J49/'Financial Statements'!J6 -> 0.044227775 | K17: ='Financial Statements'!K49/'Financial Statements'!K6 -> 0.044302551 | L17: 0.05 | M17: 0.04 | N17: 0.03 | O17: 0.02 | P17: 0.04
A18: Accruals/Sales | C18: ='Financial Statements'!C50/'Financial Statements'!C6 -> 0.021157685 | D18: ='Financial Statements'!D50/'Financial Statements'!D6 -> 0.025759768 | E18: ='Financial Statements'!E50/'Financial Statements'!E6 -> 0.023059502 | F18: ='Financial Statements'!F50/'Financial Statements'!F6 -> 0.017070673 | G18: ='Financial Statements'!G50/'Financial Statements'!G6 -> 0.020424986 | H18: ='Financial Statements'!H50/'Financial Statements'!H6 -> 0.017811094 | I18: ='Financial Statements'!I50/'Financial Statements'!I6 -> 0.015196552 | J18: ='Financial Statements'!J50/'Financial Statements'!J6 -> 0.01964855 | K18: ='Financial Statements'!K50/'Financial Statements'!K6 -> 0.011079741 | L18: 0.04 | M18: 0.03 | N18: 0.03 | O18: 0.03 | P18: 0.03
A19: Unearned Revenue/Sales | C19: ='Financial Statements'!C54/'Financial Statements'!C6 -> 0.064271457 | D19: ='Financial Statements'!D54/'Financial Statements'!D6 -> 0.012301013 | E19: ='Financial Statements'!E54/'Financial Statements'!E6 -> 0.0054560428 | F19: ='Financial Statements'!F54/'Financial Statements'!F6 -> 0.0078525094 | G19: ='Financial Statements'!G54/'Financial Statements'!G6 -> 0.012914453 | H19: ='Financial Statements'!H54/'Financial Statements'!H6 -> 0.017271364 | I19: ='Financial Statements'!I54/'Financial Statements'!I6 -> 0.011146615 | J19: ='Financial Statements'!J54/'Financial Statements'!J6 -> 0.013123749 | K19: ='Financial Statements'!K54/'Financial Statements'!K6 -> 0.012540626 | L19: 0.02 | M19: 0.01 | N19: 0.01 | O19: 0.01 | P19: 0.01
A20: Other Current Liabilities/Sales | C20: ='Financial Statements'!C55/'Financial Statements'!C6 -> 0.041516966 | D20: ='Financial Statements'!D55/'Financial Statements'!D6 -> 0.034153401 | E20: ='Financial Statements'!E55/'Financial Statements'!E6 -> 0.023883055 | F20: ='Financial Statements'!F55/'Financial Statements'!F6 -> 0.037128713 | G20: ='Financial Statements'!G55/'Financial Statements'!G6 -> 0.053214875 | H20: ='Financial Statements'!H55/'Financial Statements'!H6 -> 0.071484258 | I20: ='Financial Statements'!I55/'Financial Statements'!I6 -> 0.058222486 | J20: ='Financial Statements'!J55/'Financial Statements'!J6 -> 0.096129606 | K20: ='Financial Statements'!K55/'Financial Statements'!K6 -> 0.077459703 | L20: 0.08 | M20: 0.03 | N20: 0.03 | O20: 0.02 | P20: 0.04

Sheet Valuation
C1: Forecast 2025 | D1: Forecast 2026 | E1: Forecast 2027 | F1: Forecast 2028 | G1: Forecast 2029
A2: Net Income | C2: ='Financial Statements'!L34 -> 20104.26 | D2: ='Financial Statements'!M34 -> 23119.899 | E2: ='Financial Statements'!N34 -> 27743.879 | F2: ='Financial Statements'!O34 -> 34679.849 | G2: ='Financial Statements'!P34 -> 45083.803
A3: Change in Non-Cash WC | C3: ='Financial Statements'!S11 -> -7193426.2 | D3: ='Financial Statements'!T11 -> -7564004.4 | E3: ='Financial Statements'!U11 -> -3720248.6 | F3: ='Financial Statements'!V11 -> -8470360.3 | G3: ='Financial Statements'!W11 -> -567593.52
A4: Change in Net PPE | C4: ='Financial Statements'!L38-'Financial Statements'!K38 -> 6802.556 | D4: ='Financial Statements'!M38-'Financial Statements'!L38 -> 1809.3834 | E4: ='Financial Statements'!N38-'Financial Statements'!M38 -> 2774.3879 | F4: ='Financial Statements'!O38-'Financial Statements'!N38 -> 4161.5818 | G4: ='Financial Statements'!P38-'Financial Statements'!O38 -> 6242.3727
A5: FCFE | C5: =C2-C3-C4 -> 7206727.9 | D5: =D2-D3-D4 -> 7585315 | E5: =E2-E3-E4 -> 3745218.1 | F5: =F2-F3-F4 -> 8500878.6 | G5: =G2-G3-G4 -> 606434.95
G6: =G5*(1+B22)/(B20-B22) -> 8615558.6 | H6: Terminal Value
A7: Cfs to Discount | C7: =C5+C6 -> 7206727.9 | D7: =D5+D6 -> 7585315 | E7: =E5+E6 -> 3745218.1 | F7: =F5+F6 -> 8500878.6 | G7: =G5+G6 -> 9221993.6
A9: Estimated Value | B9: =NPV(B20,C7:G7) -> 26987145
A10: Estimated Share Price | B10: =B9/B24 -> 10930.395
A12: Current Share Price | B12: 1208
A16: ERi​=Rf​+βi​(ERm​−Rf​)
A17: Expected return for the market | B17: 0.08
A18: Beta | B18: 1.75
A19: rf | B19: 0.05
A20: Require return | B20: =B19+B18*(B17-B19) -> 0.1025
A22: Long Term Growth Rate | B22: 0.03
A24: Shares Outstanding | B24: 2469

Sheet Input sheet
